[{"lat":42.6766303,"lon":0.0857878,"alt":null,"dist":0,"pos":0},{"lat":42.6768038,"lon":0.0848436,"alt":null,"dist":79.6,"pos":0},{"lat":42.6773244,"lon":0.0845003,"alt":null,"dist":143.9,"pos":0},{"lat":42.6777346,"lon":0.0843287,"alt":null,"dist":191.6,"pos":0},{"lat":42.6780343,"lon":0.0840282,"alt":null,"dist":233,"pos":0},{"lat":42.6785075,"lon":0.0836635,"alt":null,"dist":293.5,"pos":0},{"lat":42.6789492,"lon":0.0833845,"alt":null,"dist":347.6,"pos":0},{"lat":42.6795171,"lon":0.0831485,"alt":null,"dist":413.7,"pos":0},{"lat":42.6798957,"lon":0.0830841,"alt":null,"dist":456.1,"pos":0},{"lat":42.6801797,"lon":0.0826335,"alt":null,"dist":504.6,"pos":0},{"lat":42.6804478,"lon":0.0820327,"alt":null,"dist":562.1,"pos":0},{"lat":42.6806371,"lon":0.0815177,"alt":null,"dist":609.1,"pos":0},{"lat":42.6806687,"lon":0.0811529,"alt":null,"dist":639.2,"pos":0},{"lat":42.6808107,"lon":0.0811744,"alt":null,"dist":655.1,"pos":0},{"lat":42.6809053,"lon":0.0807238,"alt":null,"dist":693.4,"pos":0},{"lat":42.6810473,"lon":0.0801444,"alt":null,"dist":743.3,"pos":0},{"lat":42.681205,"lon":0.0796723,"alt":null,"dist":785.7,"pos":0},{"lat":42.6813943,"lon":0.0792432,"alt":null,"dist":826.6,"pos":0},{"lat":42.6815047,"lon":0.0784707,"alt":null,"dist":890.9,"pos":0},{"lat":42.6814101,"lon":0.0774193,"alt":null,"dist":977.5,"pos":0},{"lat":42.6814259,"lon":0.0770545,"alt":null,"dist":1007.4,"pos":0},{"lat":42.6813943,"lon":0.0754452,"alt":null,"dist":1139,"pos":0},{"lat":42.681347,"lon":0.0744367,"alt":null,"dist":1221.6,"pos":0},{"lat":42.6814101,"lon":0.0735784,"alt":null,"dist":1292.1,"pos":0},{"lat":42.6813154,"lon":0.0729561,"alt":null,"dist":1344,"pos":0},{"lat":42.6814259,"lon":0.0722265,"alt":null,"dist":1404.9,"pos":0},{"lat":42.6817413,"lon":0.0728703,"alt":null,"dist":1468.2,"pos":0},{"lat":42.6819622,"lon":0.0725269,"alt":null,"dist":1505.5,"pos":0},{"lat":42.682325,"lon":0.0725913,"alt":null,"dist":1546.1,"pos":0},{"lat":42.6824512,"lon":0.0721836,"alt":null,"dist":1582.3,"pos":0},{"lat":42.6820884,"lon":0.0718832,"alt":null,"dist":1629.5,"pos":0},{"lat":42.6825616,"lon":0.0715184,"alt":null,"dist":1690,"pos":0},{"lat":42.683019,"lon":0.0713468,"alt":null,"dist":1742.8,"pos":0},{"lat":42.6834134,"lon":0.0712824,"alt":null,"dist":1786.9,"pos":0},{"lat":42.6837289,"lon":0.0708532,"alt":null,"dist":1836.6,"pos":0},{"lat":42.6840601,"lon":0.0703168,"alt":null,"dist":1893.8,"pos":0},{"lat":42.6842494,"lon":0.0699949,"alt":null,"dist":1927.5,"pos":0},{"lat":42.6844544,"lon":0.0695229,"alt":null,"dist":1972.3,"pos":0},{"lat":42.6848015,"lon":0.0690079,"alt":null,"dist":2029.4,"pos":0},{"lat":42.6849907,"lon":0.0688362,"alt":null,"dist":2054.7,"pos":0},{"lat":42.68518,"lon":0.0682783,"alt":null,"dist":2104.9,"pos":0},{"lat":42.685527,"lon":0.068171,"alt":null,"dist":2144.5,"pos":0},{"lat":42.6857952,"lon":0.0677204,"alt":null,"dist":2191.9,"pos":0},{"lat":42.6858188,"lon":0.0670874,"alt":null,"dist":2243.7,"pos":0},{"lat":42.6858109,"lon":0.0666797,"alt":null,"dist":2277.1,"pos":0},{"lat":42.6860318,"lon":0.0661433,"alt":null,"dist":2327.3,"pos":0},{"lat":42.686292,"lon":0.0656819,"alt":null,"dist":2374.8,"pos":0},{"lat":42.6864576,"lon":0.0653279,"alt":null,"dist":2409.1,"pos":0},{"lat":42.6865681,"lon":0.0651133,"alt":null,"dist":2430.6,"pos":0},{"lat":42.6865917,"lon":0.0645339,"alt":null,"dist":2478,"pos":0},{"lat":42.6865602,"lon":0.064019,"alt":null,"dist":2520.2,"pos":0},{"lat":42.6866469,"lon":0.0637507,"alt":null,"dist":2544.2,"pos":0},{"lat":42.6868677,"lon":0.0632358,"alt":null,"dist":2592.9,"pos":0},{"lat":42.687057,"lon":0.0630748,"alt":null,"dist":2617.7,"pos":0},{"lat":42.6872384,"lon":0.0624633,"alt":null,"dist":2671.6,"pos":0},{"lat":42.6871753,"lon":0.0621092,"alt":null,"dist":2701.4,"pos":0},{"lat":42.6870964,"lon":0.0615084,"alt":null,"dist":2751.3,"pos":0},{"lat":42.6870807,"lon":0.0610042,"alt":null,"dist":2792.5,"pos":0},{"lat":42.6868599,"lon":0.0606823,"alt":null,"dist":2828.5,"pos":0},{"lat":42.6867021,"lon":0.0604784,"alt":null,"dist":2852.7,"pos":0},{"lat":42.6865128,"lon":0.0602746,"alt":null,"dist":2879.6,"pos":0},{"lat":42.68671,"lon":0.0598991,"alt":null,"dist":2917.3,"pos":0},{"lat":42.6869545,"lon":0.0595987,"alt":null,"dist":2953.9,"pos":0},{"lat":42.6870807,"lon":0.0595772,"alt":null,"dist":2968.1,"pos":0},{"lat":42.6873094,"lon":0.0598025,"alt":null,"dist":2999.5,"pos":0},{"lat":42.687404,"lon":0.0603926,"alt":null,"dist":3048.8,"pos":0},{"lat":42.6876485,"lon":0.0604355,"alt":null,"dist":3076.2,"pos":0},{"lat":42.6879718,"lon":0.0604355,"alt":null,"dist":3112.2,"pos":0},{"lat":42.6883267,"lon":0.0605643,"alt":null,"dist":3153,"pos":0},{"lat":42.6886027,"lon":0.0606608,"alt":null,"dist":3184.7,"pos":0},{"lat":42.6887526,"lon":0.0606072,"alt":null,"dist":3201.9,"pos":0},{"lat":42.6889813,"lon":0.060178,"alt":null,"dist":3245.3,"pos":0},{"lat":42.6891153,"lon":0.059588,"alt":null,"dist":3295.7,"pos":0},{"lat":42.689068,"lon":0.0594485,"alt":null,"dist":3308.3,"pos":0},{"lat":42.6889024,"lon":0.0592554,"alt":null,"dist":3332.6,"pos":0},{"lat":42.6890838,"lon":0.0590086,"alt":null,"dist":3361.1,"pos":0},{"lat":42.6887762,"lon":0.0588369,"alt":null,"dist":3398.1,"pos":0},{"lat":42.6887762,"lon":0.0583649,"alt":null,"dist":3436.6,"pos":0},{"lat":42.6884529,"lon":0.0582254,"alt":null,"dist":3474.3,"pos":0},{"lat":42.6882321,"lon":0.0579786,"alt":null,"dist":3506.1,"pos":0},{"lat":42.6881453,"lon":0.0575066,"alt":null,"dist":3545.9,"pos":0},{"lat":42.6880822,"lon":0.0571632,"alt":null,"dist":3574.8,"pos":0},{"lat":42.6882636,"lon":0.0570667,"alt":null,"dist":3596.5,"pos":0},{"lat":42.6882794,"lon":0.0567019,"alt":null,"dist":3626.3,"pos":0},{"lat":42.6885081,"lon":0.0565946,"alt":null,"dist":3653.2,"pos":0},{"lat":42.6883188,"lon":0.0557256,"alt":null,"dist":3727.3,"pos":0},{"lat":42.6885791,"lon":0.055511,"alt":null,"dist":3761.2,"pos":0},{"lat":42.6885633,"lon":0.0550497,"alt":null,"dist":3798.9,"pos":0},{"lat":42.6881611,"lon":0.0544703,"alt":null,"dist":3864.1,"pos":0},{"lat":42.6881611,"lon":0.0541592,"alt":null,"dist":3889.5,"pos":0},{"lat":42.6882557,"lon":0.0539017,"alt":null,"dist":3913,"pos":0},{"lat":42.6882715,"lon":0.0534832,"alt":null,"dist":3947.3,"pos":0},{"lat":42.6883188,"lon":0.053215,"alt":null,"dist":3969.8,"pos":0},{"lat":42.6885002,"lon":0.0529361,"alt":null,"dist":4000.2,"pos":0},{"lat":42.6886027,"lon":0.0528181,"alt":null,"dist":4015.2,"pos":0},{"lat":42.6889024,"lon":0.0529361,"alt":null,"dist":4049.9,"pos":0},{"lat":42.6890601,"lon":0.0530112,"alt":null,"dist":4068.4,"pos":0},{"lat":42.6893283,"lon":0.0527644,"alt":null,"dist":4104.4,"pos":0},{"lat":42.6890759,"lon":0.0524104,"alt":null,"dist":4144.8,"pos":0},{"lat":42.6892179,"lon":0.0521958,"alt":null,"dist":4168.4,"pos":0},{"lat":42.6893756,"lon":0.0520885,"alt":null,"dist":4188,"pos":0},{"lat":42.6897068,"lon":0.0522709,"alt":null,"dist":4227.7,"pos":0},{"lat":42.6900538,"lon":0.0523782,"alt":null,"dist":4267.3,"pos":0},{"lat":42.6902904,"lon":0.0522709,"alt":null,"dist":4295,"pos":0},{"lat":42.6904639,"lon":0.0523031,"alt":null,"dist":4314.5,"pos":0},{"lat":42.6904875,"lon":0.0517344,"alt":null,"dist":4361,"pos":0},{"lat":42.6904796,"lon":0.0511444,"alt":null,"dist":4409.2,"pos":0},{"lat":42.6904323,"lon":0.0509405,"alt":null,"dist":4426.7,"pos":0},{"lat":42.69059,"lon":0.0508332,"alt":null,"dist":4446.3,"pos":0},{"lat":42.6904875,"lon":0.0506616,"alt":null,"dist":4464.4,"pos":0},{"lat":42.6907083,"lon":0.0504899,"alt":null,"dist":4492.7,"pos":0},{"lat":42.6905427,"lon":0.0501144,"alt":null,"dist":4528.5,"pos":0},{"lat":42.6903061,"lon":0.0499749,"alt":null,"dist":4557.1,"pos":0},{"lat":42.6903456,"lon":0.0497711,"alt":null,"dist":4574.4,"pos":0},{"lat":42.690109,"lon":0.0495672,"alt":null,"dist":4605.5,"pos":0},{"lat":42.6903535,"lon":0.0493312,"alt":null,"dist":4638.8,"pos":0},{"lat":42.6900853,"lon":0.048945,"alt":null,"dist":4682.3,"pos":0},{"lat":42.6902904,"lon":0.0488269,"alt":null,"dist":4707,"pos":0},{"lat":42.6900932,"lon":0.0486767,"alt":null,"dist":4732.2,"pos":0},{"lat":42.6904165,"lon":0.0486445,"alt":null,"dist":4768.2,"pos":0},{"lat":42.6901326,"lon":0.04843,"alt":null,"dist":4804.3,"pos":0},{"lat":42.6903613,"lon":0.0483012,"alt":null,"dist":4831.8,"pos":0},{"lat":42.6900222,"lon":0.0480866,"alt":null,"dist":4873.4,"pos":0},{"lat":42.6896595,"lon":0.0479472,"alt":null,"dist":4915.3,"pos":0},{"lat":42.6894071,"lon":0.0479686,"alt":null,"dist":4943.5,"pos":0},{"lat":42.6891784,"lon":0.0483656,"alt":null,"dist":4984.7,"pos":0},{"lat":42.6890049,"lon":0.0485373,"alt":null,"dist":5008.5,"pos":0},{"lat":42.6887683,"lon":0.0479257,"alt":null,"dist":5065,"pos":0},{"lat":42.6888709,"lon":0.0473464,"alt":null,"dist":5113.7,"pos":0},{"lat":42.689068,"lon":0.0467885,"alt":null,"dist":5164.3,"pos":0},{"lat":42.6892179,"lon":0.0463808,"alt":null,"dist":5201.6,"pos":0},{"lat":42.6892967,"lon":0.0459945,"alt":null,"dist":5234.4,"pos":0},{"lat":42.6893992,"lon":0.0455654,"alt":null,"dist":5271.2,"pos":0},{"lat":42.68962,"lon":0.0450718,"alt":null,"dist":5318.5,"pos":0},{"lat":42.6898093,"lon":0.044589,"alt":null,"dist":5363.2,"pos":0},{"lat":42.689967,"lon":0.0441062,"alt":null,"dist":5406.4,"pos":0},{"lat":42.6900617,"lon":0.0438488,"alt":null,"dist":5429.9,"pos":0},{"lat":42.6901642,"lon":0.0434303,"alt":null,"dist":5465.9,"pos":0},{"lat":42.6903377,"lon":0.0428188,"alt":null,"dist":5519.5,"pos":0},{"lat":42.6904402,"lon":0.0423038,"alt":null,"dist":5563.1,"pos":0},{"lat":42.6906295,"lon":0.0419927,"alt":null,"dist":5596.1,"pos":0},{"lat":42.690866,"lon":0.0416064,"alt":null,"dist":5637.2,"pos":0},{"lat":42.6910316,"lon":0.0412309,"alt":null,"dist":5673,"pos":0},{"lat":42.6912446,"lon":0.0409091,"alt":null,"dist":5708.4,"pos":0},{"lat":42.6914181,"lon":0.0405443,"alt":null,"dist":5743.9,"pos":0},{"lat":42.6915758,"lon":0.0402761,"alt":null,"dist":5772,"pos":0},{"lat":42.6917571,"lon":0.0399649,"alt":null,"dist":5804.4,"pos":0},{"lat":42.6919306,"lon":0.0396323,"alt":null,"dist":5837.8,"pos":0},{"lat":42.6920647,"lon":0.0393856,"alt":null,"dist":5862.9,"pos":0},{"lat":42.6922934,"lon":0.0390851,"alt":null,"dist":5898.2,"pos":0},{"lat":42.6924747,"lon":0.0387418,"alt":null,"dist":5932.8,"pos":0},{"lat":42.6926325,"lon":0.0384414,"alt":null,"dist":5962.9,"pos":0},{"lat":42.6927271,"lon":0.0383234,"alt":null,"dist":5977.2,"pos":0},{"lat":42.6929637,"lon":0.0383234,"alt":null,"dist":6003.5,"pos":0},{"lat":42.6931923,"lon":0.0384092,"alt":null,"dist":6029.9,"pos":0},{"lat":42.6932949,"lon":0.0384307,"alt":null,"dist":6041.4,"pos":0},{"lat":42.6935157,"lon":0.0388813,"alt":null,"dist":6085.7,"pos":0},{"lat":42.6937049,"lon":0.0385702,"alt":null,"dist":6118.7,"pos":0},{"lat":42.6937759,"lon":0.0382912,"alt":null,"dist":6142.8,"pos":0},{"lat":42.6938705,"lon":0.0379157,"alt":null,"dist":6175.3,"pos":0},{"lat":42.6939021,"lon":0.0376582,"alt":null,"dist":6196.6,"pos":0},{"lat":42.6938469,"lon":0.0370574,"alt":null,"dist":6246.1,"pos":0},{"lat":42.6936497,"lon":0.0364888,"alt":null,"dist":6297.5,"pos":0},{"lat":42.6936734,"lon":0.0363064,"alt":null,"dist":6312.6,"pos":0},{"lat":42.6937917,"lon":0.0357056,"alt":null,"dist":6363.4,"pos":0},{"lat":42.6940124,"lon":0.0352871,"alt":null,"dist":6405.5,"pos":0},{"lat":42.6942096,"lon":0.0348365,"alt":null,"dist":6448.4,"pos":0},{"lat":42.6944619,"lon":0.0344288,"alt":null,"dist":6491.9,"pos":0},{"lat":42.6945408,"lon":0.0341713,"alt":null,"dist":6514.7,"pos":0},{"lat":42.6946591,"lon":0.0336027,"alt":null,"dist":6563,"pos":0},{"lat":42.6947695,"lon":0.0329483,"alt":null,"dist":6617.9,"pos":0},{"lat":42.6947143,"lon":0.0322294,"alt":null,"dist":6677,"pos":0},{"lat":42.6947931,"lon":0.0315428,"alt":null,"dist":6733.8,"pos":0},{"lat":42.6949824,"lon":0.030942,"alt":null,"dist":6787.2,"pos":0},{"lat":42.695148,"lon":0.0304377,"alt":null,"dist":6832.3,"pos":0},{"lat":42.695282,"lon":0.0299978,"alt":null,"dist":6871.3,"pos":0},{"lat":42.6954713,"lon":0.0293648,"alt":null,"dist":6927.1,"pos":0},{"lat":42.6955974,"lon":0.029,"alt":null,"dist":6960.1,"pos":0},{"lat":42.6957394,"lon":0.0284958,"alt":null,"dist":7004.2,"pos":0},{"lat":42.6958734,"lon":0.0279915,"alt":null,"dist":7048,"pos":0},{"lat":42.6960311,"lon":0.0272834,"alt":null,"dist":7108.5,"pos":0},{"lat":42.6961257,"lon":0.0267255,"alt":null,"dist":7155.3,"pos":0},{"lat":42.6962677,"lon":0.0260925,"alt":null,"dist":7209.4,"pos":0},{"lat":42.6964411,"lon":0.0255239,"alt":null,"dist":7259.7,"pos":0},{"lat":42.6966067,"lon":0.0249445,"alt":null,"dist":7310.5,"pos":0},{"lat":42.6967802,"lon":0.0243223,"alt":null,"dist":7364.9,"pos":0},{"lat":42.6969064,"lon":0.0237107,"alt":null,"dist":7416.8,"pos":0},{"lat":42.6972218,"lon":0.0232065,"alt":null,"dist":7470.9,"pos":0},{"lat":42.6975451,"lon":0.02267,"alt":null,"dist":7527.6,"pos":0},{"lat":42.6976712,"lon":0.022434,"alt":null,"dist":7551.4,"pos":0},{"lat":42.6977816,"lon":0.0219834,"alt":null,"dist":7590.2,"pos":0},{"lat":42.6979236,"lon":0.0215435,"alt":null,"dist":7629.5,"pos":0},{"lat":42.6980576,"lon":0.0210929,"alt":null,"dist":7669.2,"pos":0},{"lat":42.6982074,"lon":0.0207281,"alt":null,"dist":7703.4,"pos":0},{"lat":42.6983888,"lon":0.0203419,"alt":null,"dist":7740.8,"pos":0},{"lat":42.6987357,"lon":0.0199127,"alt":null,"dist":7793,"pos":0},{"lat":42.6989486,"lon":0.0197732,"alt":null,"dist":7819.2,"pos":0},{"lat":42.6990432,"lon":0.0191081,"alt":null,"dist":7874.6,"pos":0},{"lat":42.6992246,"lon":0.0187111,"alt":null,"dist":7912.8,"pos":0},{"lat":42.6992955,"lon":0.018518,"alt":null,"dist":7930.4,"pos":0},{"lat":42.699469,"lon":0.0180352,"alt":null,"dist":7974.4,"pos":0},{"lat":42.6997529,"lon":0.0177348,"alt":null,"dist":8014.4,"pos":0},{"lat":42.6999421,"lon":0.017091,"alt":null,"dist":8071,"pos":0},{"lat":42.7001156,"lon":0.0170267,"alt":null,"dist":8091,"pos":0},{"lat":42.7003915,"lon":0.0164258,"alt":null,"dist":8148.9,"pos":0},{"lat":42.7004073,"lon":0.0162327,"alt":null,"dist":8164.8,"pos":0},{"lat":42.7005808,"lon":0.0160182,"alt":null,"dist":8190.9,"pos":0},{"lat":42.7006675,"lon":0.0156426,"alt":null,"dist":8223,"pos":0},{"lat":42.7008567,"lon":0.0153959,"alt":null,"dist":8252.2,"pos":0},{"lat":42.7009277,"lon":0.0149667,"alt":null,"dist":8288.1,"pos":0},{"lat":42.7011169,"lon":0.0147951,"alt":null,"dist":8313.4,"pos":0},{"lat":42.701109,"lon":0.0145376,"alt":null,"dist":8334.5,"pos":0},{"lat":42.701385,"lon":0.0146234,"alt":null,"dist":8365.9,"pos":0},{"lat":42.701724,"lon":0.0144517,"alt":null,"dist":8406.2,"pos":0},{"lat":42.7019054,"lon":0.0143981,"alt":null,"dist":8426.8,"pos":0},{"lat":42.7018344,"lon":0.0147629,"alt":null,"dist":8457.6,"pos":0},{"lat":42.7018265,"lon":0.0152886,"alt":null,"dist":8500.6,"pos":0},{"lat":42.7017634,"lon":0.015986,"alt":null,"dist":8558,"pos":0},{"lat":42.701795,"lon":0.0165224,"alt":null,"dist":8602,"pos":0},{"lat":42.7016609,"lon":0.017091,"alt":null,"dist":8650.8,"pos":0},{"lat":42.7017319,"lon":0.0174451,"alt":null,"dist":8680.8,"pos":0},{"lat":42.7016215,"lon":0.0180995,"alt":null,"dist":8735.7,"pos":0},{"lat":42.7016215,"lon":0.0186253,"alt":null,"dist":8778.6,"pos":0},{"lat":42.7016058,"lon":0.0190008,"alt":null,"dist":8809.4,"pos":0},{"lat":42.7016531,"lon":0.0193655,"alt":null,"dist":8839.6,"pos":0},{"lat":42.7017398,"lon":0.0196016,"alt":null,"dist":8861.2,"pos":0},{"lat":42.7018186,"lon":0.02002,"alt":null,"dist":8896.5,"pos":0},{"lat":42.7019606,"lon":0.0204813,"alt":null,"dist":8937.4,"pos":0},{"lat":42.7022365,"lon":0.0209749,"alt":null,"dist":8988,"pos":0},{"lat":42.7023942,"lon":0.0215542,"alt":null,"dist":9038.5,"pos":0},{"lat":42.7024021,"lon":0.0220907,"alt":null,"dist":9082.4,"pos":0},{"lat":42.7023627,"lon":0.0230885,"alt":null,"dist":9164,"pos":0},{"lat":42.7023784,"lon":0.0235391,"alt":null,"dist":9200.9,"pos":0},{"lat":42.7024415,"lon":0.0238502,"alt":null,"dist":9227.2,"pos":0},{"lat":42.7025204,"lon":0.0240755,"alt":null,"dist":9247.6,"pos":0},{"lat":42.7024652,"lon":0.0236785,"alt":null,"dist":9280.7,"pos":0},{"lat":42.7023863,"lon":0.0231421,"alt":null,"dist":9325.4,"pos":0},{"lat":42.7024021,"lon":0.0226915,"alt":null,"dist":9362.2,"pos":0},{"lat":42.7023784,"lon":0.0219512,"alt":null,"dist":9422.8,"pos":0},{"lat":42.7022917,"lon":0.0214362,"alt":null,"dist":9465.9,"pos":0},{"lat":42.7021498,"lon":0.0210392,"alt":null,"dist":9502,"pos":0},{"lat":42.7020315,"lon":0.0207174,"alt":null,"dist":9531.4,"pos":0},{"lat":42.7018186,"lon":0.0201702,"alt":null,"dist":9582,"pos":0},{"lat":42.7016373,"lon":0.019902,"alt":null,"dist":9611.8,"pos":0},{"lat":42.7014165,"lon":0.0199771,"alt":null,"dist":9637.1,"pos":0},{"lat":42.7009671,"lon":0.0206208,"alt":null,"dist":9709.7,"pos":0},{"lat":42.7006675,"lon":0.0211573,"alt":null,"dist":9764.7,"pos":0},{"lat":42.7005886,"lon":0.0219405,"alt":null,"dist":9829.3,"pos":0},{"lat":42.7004861,"lon":0.0229168,"alt":null,"dist":9909.9,"pos":0},{"lat":42.7002654,"lon":0.0239253,"alt":null,"dist":9995.9,"pos":0},{"lat":42.7001077,"lon":0.0243115,"alt":null,"dist":10032,"pos":0},{"lat":42.6996504,"lon":0.0249875,"alt":null,"dist":10107.1,"pos":0},{"lat":42.6993823,"lon":0.0253952,"alt":null,"dist":10151.8,"pos":0},{"lat":42.6990511,"lon":0.0258994,"alt":null,"dist":10207.1,"pos":0},{"lat":42.6988224,"lon":0.026232,"alt":null,"dist":10244.3,"pos":0},{"lat":42.6984992,"lon":0.0266075,"alt":null,"dist":10291.5,"pos":0},{"lat":42.6980418,"lon":0.0269616,"alt":null,"dist":10350.1,"pos":0},{"lat":42.6975451,"lon":0.0274551,"alt":null,"dist":10418.4,"pos":0},{"lat":42.6970877,"lon":0.0279379,"alt":null,"dist":10482.8,"pos":0},{"lat":42.696725,"lon":0.0285816,"alt":null,"dist":10549.1,"pos":0},{"lat":42.696244,"lon":0.0290644,"alt":null,"dist":10615.6,"pos":0},{"lat":42.6958892,"lon":0.0295472,"alt":null,"dist":10671.4,"pos":0},{"lat":42.6954555,"lon":0.0302553,"alt":null,"dist":10746.7,"pos":0},{"lat":42.6952189,"lon":0.0305986,"alt":null,"dist":10785.2,"pos":0},{"lat":42.6950297,"lon":0.0310814,"alt":null,"dist":10829.9,"pos":0},{"lat":42.6948404,"lon":0.0316286,"alt":null,"dist":10879.3,"pos":0},{"lat":42.6946827,"lon":0.032047,"alt":null,"dist":10917.7,"pos":0},{"lat":42.6947221,"lon":0.0328302,"alt":null,"dist":10981.9,"pos":0},{"lat":42.6946196,"lon":0.0335276,"alt":null,"dist":11040,"pos":0},{"lat":42.6945487,"lon":0.0340641,"alt":null,"dist":11084.6,"pos":0},{"lat":42.6943831,"lon":0.0344825,"alt":null,"dist":11123.4,"pos":0},{"lat":42.6941938,"lon":0.0350189,"alt":null,"dist":11172,"pos":0},{"lat":42.6939651,"lon":0.0353086,"alt":null,"dist":11206.8,"pos":0},{"lat":42.6938153,"lon":0.0359201,"alt":null,"dist":11259.4,"pos":0},{"lat":42.6936497,"lon":0.0362098,"alt":null,"dist":11289.4,"pos":0},{"lat":42.693697,"lon":0.036875,"alt":null,"dist":11344.1,"pos":0},{"lat":42.6938153,"lon":0.0372934,"alt":null,"dist":11380.7,"pos":0},{"lat":42.6939809,"lon":0.0376475,"alt":null,"dist":11415,"pos":0},{"lat":42.6938232,"lon":0.0382376,"alt":null,"dist":11466.3,"pos":0},{"lat":42.6935945,"lon":0.0386775,"alt":null,"dist":11510.3,"pos":0},{"lat":42.6934683,"lon":0.0389886,"alt":null,"dist":11539.4,"pos":0},{"lat":42.693287,"lon":0.0385487,"alt":null,"dist":11580.6,"pos":0},{"lat":42.6931056,"lon":0.03842,"alt":null,"dist":11603.4,"pos":0},{"lat":42.6928059,"lon":0.0383985,"alt":null,"dist":11636.7,"pos":0},{"lat":42.6925457,"lon":0.0385594,"alt":null,"dist":11668.5,"pos":0},{"lat":42.6922539,"lon":0.0389886,"alt":null,"dist":11716.3,"pos":0},{"lat":42.6920016,"lon":0.0394285,"alt":null,"dist":11761.9,"pos":0},{"lat":42.6918045,"lon":0.039804,"alt":null,"dist":11799.6,"pos":0},{"lat":42.6915679,"lon":0.0402117,"alt":null,"dist":11842.1,"pos":0},{"lat":42.6912603,"lon":0.0407696,"alt":null,"dist":11899.1,"pos":0},{"lat":42.6910316,"lon":0.0411451,"alt":null,"dist":11938.9,"pos":0},{"lat":42.6907477,"lon":0.0417459,"alt":null,"dist":11997.3,"pos":0},{"lat":42.6904796,"lon":0.0421751,"alt":null,"dist":12043.3,"pos":0},{"lat":42.6903692,"lon":0.0425291,"alt":null,"dist":12074.8,"pos":0},{"lat":42.6902194,"lon":0.0430763,"alt":null,"dist":12122.5,"pos":0},{"lat":42.6900696,"lon":0.0436127,"alt":null,"dist":12169.4,"pos":0},{"lat":42.6898409,"lon":0.0443208,"alt":null,"dist":12232.6,"pos":0},{"lat":42.689762,"lon":0.0448251,"alt":null,"dist":12274.7,"pos":0},{"lat":42.6894387,"lon":0.045383,"alt":null,"dist":12332.8,"pos":0},{"lat":42.6892179,"lon":0.0459516,"alt":null,"dist":12385.4,"pos":0},{"lat":42.6891784,"lon":0.0462949,"alt":null,"dist":12413.8,"pos":0},{"lat":42.6889182,"lon":0.0470352,"alt":null,"dist":12480.8,"pos":0},{"lat":42.6888235,"lon":0.0479472,"alt":null,"dist":12556.1,"pos":0},{"lat":42.688934,"lon":0.0485265,"alt":null,"dist":12605,"pos":0},{"lat":42.6891705,"lon":0.0484729,"alt":null,"dist":12631.7,"pos":0},{"lat":42.6894702,"lon":0.0480223,"alt":null,"dist":12681.4,"pos":0},{"lat":42.6899591,"lon":0.0480008,"alt":null,"dist":12735.8,"pos":0},{"lat":42.6904244,"lon":0.0482798,"alt":null,"dist":12792.3,"pos":0},{"lat":42.6900932,"lon":0.0483871,"alt":null,"dist":12830.1,"pos":0},{"lat":42.690456,"lon":0.0486124,"alt":null,"dist":12874.5,"pos":0},{"lat":42.6900459,"lon":0.0486767,"alt":null,"dist":12920.4,"pos":0},{"lat":42.6903298,"lon":0.048902,"alt":null,"dist":12956.9,"pos":0},{"lat":42.6901011,"lon":0.0490522,"alt":null,"dist":12985.2,"pos":0},{"lat":42.6904165,"lon":0.0492454,"alt":null,"dist":13023.6,"pos":0},{"lat":42.6900696,"lon":0.0494921,"alt":null,"dist":13067.2,"pos":0},{"lat":42.6904008,"lon":0.0498247,"alt":null,"dist":13112.9,"pos":0},{"lat":42.6902982,"lon":0.0500607,"alt":null,"dist":13135.4,"pos":0},{"lat":42.6906216,"lon":0.0501788,"alt":null,"dist":13172.6,"pos":0},{"lat":42.6907399,"lon":0.0505435,"alt":null,"dist":13205.2,"pos":0},{"lat":42.6904639,"lon":0.0507259,"alt":null,"dist":13239.3,"pos":0},{"lat":42.6906295,"lon":0.0509191,"alt":null,"dist":13263.5,"pos":0},{"lat":42.6904087,"lon":0.0510049,"alt":null,"dist":13289.1,"pos":0},{"lat":42.6904481,"lon":0.0515842,"alt":null,"dist":13336.6,"pos":0},{"lat":42.6905191,"lon":0.0520027,"alt":null,"dist":13371.7,"pos":0},{"lat":42.6904165,"lon":0.0524104,"alt":null,"dist":13407,"pos":0},{"lat":42.6902036,"lon":0.0522065,"alt":null,"dist":13435.9,"pos":0},{"lat":42.689967,"lon":0.0523996,"alt":null,"dist":13466.6,"pos":0},{"lat":42.6897541,"lon":0.0522065,"alt":null,"dist":13495,"pos":0},{"lat":42.6894623,"lon":0.052067,"alt":null,"dist":13529.4,"pos":0},{"lat":42.6893835,"lon":0.0521851,"alt":null,"dist":13542.5,"pos":0},{"lat":42.68921,"lon":0.0522816,"alt":null,"dist":13563.3,"pos":0},{"lat":42.6889813,"lon":0.0524211,"alt":null,"dist":13591.2,"pos":0},{"lat":42.6892179,"lon":0.0527215,"alt":null,"dist":13627.2,"pos":0},{"lat":42.6893125,"lon":0.0528502,"alt":null,"dist":13642,"pos":0},{"lat":42.689139,"lon":0.0530326,"alt":null,"dist":13666.4,"pos":0},{"lat":42.6888472,"lon":0.0528717,"alt":null,"dist":13701.4,"pos":0},{"lat":42.6885475,"lon":0.0527859,"alt":null,"dist":13735.5,"pos":0},{"lat":42.688374,"lon":0.0532365,"alt":null,"dist":13777.1,"pos":0},{"lat":42.68824,"lon":0.0536013,"alt":null,"dist":13810.4,"pos":0},{"lat":42.6883109,"lon":0.0540304,"alt":null,"dist":13846.3,"pos":0},{"lat":42.6881138,"lon":0.0543845,"alt":null,"dist":13882.6,"pos":0},{"lat":42.6882952,"lon":0.0547814,"alt":null,"dist":13920.8,"pos":0},{"lat":42.6884766,"lon":0.0550926,"alt":null,"dist":13953.3,"pos":0},{"lat":42.6886106,"lon":0.0554037,"alt":null,"dist":13982.8,"pos":0},{"lat":42.6882636,"lon":0.0558007,"alt":null,"dist":14033.2,"pos":0},{"lat":42.6885239,"lon":0.0564981,"alt":null,"dist":14097.1,"pos":0},{"lat":42.6883346,"lon":0.0567663,"alt":null,"dist":14127.5,"pos":0},{"lat":42.6881217,"lon":0.0571203,"alt":null,"dist":14164.9,"pos":0},{"lat":42.688098,"lon":0.0575924,"alt":null,"dist":14203.6,"pos":0},{"lat":42.6883188,"lon":0.0579679,"alt":null,"dist":14242.9,"pos":0},{"lat":42.6885712,"lon":0.0582147,"alt":null,"dist":14277.4,"pos":0},{"lat":42.6888078,"lon":0.0582898,"alt":null,"dist":14304.5,"pos":0},{"lat":42.6887999,"lon":0.0587511,"alt":null,"dist":14342.2,"pos":0},{"lat":42.6890365,"lon":0.058912,"alt":null,"dist":14371.6,"pos":0},{"lat":42.6889892,"lon":0.0592768,"alt":null,"dist":14401.9,"pos":0},{"lat":42.6891548,"lon":0.0595236,"alt":null,"dist":14429.2,"pos":0},{"lat":42.6888945,"lon":0.0602424,"alt":null,"dist":14494.7,"pos":0},{"lat":42.6887841,"lon":0.0606823,"alt":null,"dist":14532.7,"pos":0},{"lat":42.6883109,"lon":0.0604784,"alt":null,"dist":14587.8,"pos":0},{"lat":42.6878851,"lon":0.0604892,"alt":null,"dist":14635.2,"pos":0},{"lat":42.6875775,"lon":0.0604784,"alt":null,"dist":14669.4,"pos":0},{"lat":42.6874277,"lon":0.0602531,"alt":null,"dist":14694.3,"pos":0},{"lat":42.6873646,"lon":0.0598133,"alt":null,"dist":14730.9,"pos":0},{"lat":42.6870807,"lon":0.0596631,"alt":null,"dist":14764.7,"pos":0},{"lat":42.6867889,"lon":0.0599313,"alt":null,"dist":14803.9,"pos":0},{"lat":42.6865128,"lon":0.0603604,"alt":null,"dist":14850.5,"pos":0},{"lat":42.6870097,"lon":0.0609612,"alt":null,"dist":14924.4,"pos":0},{"lat":42.6870334,"lon":0.0614333,"alt":null,"dist":14963.1,"pos":0},{"lat":42.6871122,"lon":0.061841,"alt":null,"dist":14997.6,"pos":0},{"lat":42.6872699,"lon":0.0623238,"alt":null,"dist":15040.8,"pos":0},{"lat":42.6872857,"lon":0.062592,"alt":null,"dist":15062.7,"pos":0},{"lat":42.6869939,"lon":0.0630426,"alt":null,"dist":15111.8,"pos":0},{"lat":42.6868835,"lon":0.0633216,"alt":null,"dist":15137.7,"pos":0},{"lat":42.6866548,"lon":0.0636327,"alt":null,"dist":15173.7,"pos":0},{"lat":42.6865286,"lon":0.0641477,"alt":null,"dist":15218.1,"pos":0},{"lat":42.6865602,"lon":0.0644374,"alt":null,"dist":15242,"pos":0},{"lat":42.6866548,"lon":0.0650167,"alt":null,"dist":15290.5,"pos":0},{"lat":42.6864655,"lon":0.0651884,"alt":null,"dist":15315.8,"pos":0},{"lat":42.6862289,"lon":0.0657248,"alt":null,"dist":15366.9,"pos":0},{"lat":42.6861264,"lon":0.0661004,"alt":null,"dist":15399.7,"pos":0},{"lat":42.6858346,"lon":0.0664973,"alt":null,"dist":15445.6,"pos":0},{"lat":42.6858504,"lon":0.0672483,"alt":null,"dist":15507,"pos":0},{"lat":42.6858425,"lon":0.0676346,"alt":null,"dist":15538.6,"pos":0},{"lat":42.68574,"lon":0.0679672,"alt":null,"dist":15568,"pos":0},{"lat":42.6855822,"lon":0.0681388,"alt":null,"dist":15590.5,"pos":0},{"lat":42.6854008,"lon":0.0681174,"alt":null,"dist":15610.8,"pos":0},{"lat":42.6853141,"lon":0.067935,"alt":null,"dist":15628.5,"pos":0},{"lat":42.6852273,"lon":0.0676453,"alt":null,"dist":15654.1,"pos":0},{"lat":42.6850538,"lon":0.0682354,"alt":null,"dist":15706,"pos":0},{"lat":42.6849355,"lon":0.0686002,"alt":null,"dist":15738.6,"pos":0},{"lat":42.6845649,"lon":0.0684822,"alt":null,"dist":15780.9,"pos":0},{"lat":42.684415,"lon":0.068804,"alt":null,"dist":15812.1,"pos":0},{"lat":42.6842573,"lon":0.0692546,"alt":null,"dist":15852.9,"pos":0},{"lat":42.6840916,"lon":0.0696623,"alt":null,"dist":15891,"pos":0},{"lat":42.683997,"lon":0.0697696,"alt":null,"dist":15904.7,"pos":0},{"lat":42.6838945,"lon":0.069437,"alt":null,"dist":15934.1,"pos":0},{"lat":42.6838945,"lon":0.0693083,"alt":null,"dist":15944.6,"pos":0},{"lat":42.6837604,"lon":0.0690615,"alt":null,"dist":15969.7,"pos":0},{"lat":42.6836579,"lon":0.0690186,"alt":null,"dist":15981.7,"pos":0},{"lat":42.6832714,"lon":0.0692654,"alt":null,"dist":16029.1,"pos":0},{"lat":42.6829638,"lon":0.0695014,"alt":null,"dist":16068.4,"pos":0},{"lat":42.6827272,"lon":0.0697803,"alt":null,"dist":16103.2,"pos":0},{"lat":42.6824512,"lon":0.0700915,"alt":null,"dist":16143.1,"pos":0},{"lat":42.6822934,"lon":0.0702524,"alt":null,"dist":16165,"pos":0},{"lat":42.6821751,"lon":0.0698984,"alt":null,"dist":16196.8,"pos":0},{"lat":42.6818675,"lon":0.069834,"alt":null,"dist":16231.4,"pos":0},{"lat":42.6815757,"lon":0.0698125,"alt":null,"dist":16263.9,"pos":0},{"lat":42.6810867,"lon":0.0699842,"alt":null,"dist":16320.1,"pos":0},{"lat":42.6808974,"lon":0.0701022,"alt":null,"dist":16343.2,"pos":0},{"lat":42.6806608,"lon":0.070703,"alt":null,"dist":16398.9,"pos":0},{"lat":42.6803611,"lon":0.0706172,"alt":null,"dist":16433,"pos":0},{"lat":42.6801797,"lon":0.0708532,"alt":null,"dist":16460.9,"pos":0},{"lat":42.6800062,"lon":0.0712931,"alt":null,"dist":16501.7,"pos":0},{"lat":42.6797538,"lon":0.0716579,"alt":null,"dist":16542.6,"pos":0},{"lat":42.6793988,"lon":0.0719583,"alt":null,"dist":16589.1,"pos":0},{"lat":42.6796828,"lon":0.0720978,"alt":null,"dist":16622.7,"pos":0},{"lat":42.6801087,"lon":0.0720978,"alt":null,"dist":16670.1,"pos":0},{"lat":42.6803532,"lon":0.0722051,"alt":null,"dist":16698.6,"pos":0},{"lat":42.680156,"lon":0.0726342,"alt":null,"dist":16740,"pos":0},{"lat":42.6798484,"lon":0.0730419,"alt":null,"dist":16787.8,"pos":0},{"lat":42.6795329,"lon":0.0733638,"alt":null,"dist":16831.6,"pos":0},{"lat":42.6792647,"lon":0.0736427,"alt":null,"dist":16869.1,"pos":0},{"lat":42.6789729,"lon":0.0739002,"alt":null,"dist":16907.8,"pos":0},{"lat":42.6785312,"lon":0.0742114,"alt":null,"dist":16963.1,"pos":0},{"lat":42.678192,"lon":0.0746727,"alt":null,"dist":17016.5,"pos":0},{"lat":42.6779239,"lon":0.0753486,"alt":null,"dist":17079.3,"pos":0},{"lat":42.6774822,"lon":0.0758421,"alt":null,"dist":17142.8,"pos":0},{"lat":42.6771036,"lon":0.0761425,"alt":null,"dist":17191.6,"pos":0},{"lat":42.6767328,"lon":0.0764859,"alt":null,"dist":17241.4,"pos":0},{"lat":42.6763621,"lon":0.0771725,"alt":null,"dist":17311.1,"pos":0},{"lat":42.6762043,"lon":0.0778162,"alt":null,"dist":17366.5,"pos":0},{"lat":42.6763779,"lon":0.0786746,"alt":null,"dist":17439.3,"pos":0},{"lat":42.6762201,"lon":0.0794899,"alt":null,"dist":17508.2,"pos":0},{"lat":42.6761886,"lon":0.0804663,"alt":null,"dist":17588.1,"pos":0},{"lat":42.6762359,"lon":0.0811851,"alt":null,"dist":17647.1,"pos":0},{"lat":42.6765199,"lon":0.0820863,"alt":null,"dist":17727.3,"pos":0},{"lat":42.6767407,"lon":0.0828803,"alt":null,"dist":17796.7,"pos":0},{"lat":42.6768196,"lon":0.0836957,"alt":null,"dist":17863.9,"pos":0},{"lat":42.6768433,"lon":0.0841355,"alt":null,"dist":17900,"pos":0},{"lat":42.6766461,"lon":0.0848866,"alt":null,"dist":17965.2,"pos":0},{"lat":42.6765514,"lon":0.0855088,"alt":null,"dist":18017.1,"pos":0}]