[{"lat":42.6731911,"lon":0.1495385,"alt":null,"dist":0,"pos":0},{"lat":42.6735224,"lon":0.1492381,"alt":null,"dist":44.3,"pos":0},{"lat":42.6737275,"lon":0.1490879,"alt":null,"dist":70.2,"pos":0},{"lat":42.6739168,"lon":0.148927,"alt":null,"dist":95,"pos":0},{"lat":42.6742087,"lon":0.1488626,"alt":null,"dist":127.9,"pos":0},{"lat":42.674469,"lon":0.1487553,"alt":null,"dist":158.1,"pos":0},{"lat":42.6746347,"lon":0.1486588,"alt":null,"dist":178.2,"pos":0},{"lat":42.6748871,"lon":0.1484978,"alt":null,"dist":209.2,"pos":0},{"lat":42.6750764,"lon":0.1483905,"alt":null,"dist":232,"pos":0},{"lat":42.6752815,"lon":0.1482189,"alt":null,"dist":258.7,"pos":0},{"lat":42.6754313,"lon":0.1479936,"alt":null,"dist":283.6,"pos":0},{"lat":42.6756601,"lon":0.1477683,"alt":null,"dist":315,"pos":0},{"lat":42.6759125,"lon":0.1475859,"alt":null,"dist":346.8,"pos":0},{"lat":42.6761018,"lon":0.1474249,"alt":null,"dist":371.6,"pos":0},{"lat":42.6763069,"lon":0.1471996,"alt":null,"dist":400.9,"pos":0},{"lat":42.6766066,"lon":0.1470172,"alt":null,"dist":437.4,"pos":0},{"lat":42.6768354,"lon":0.1467919,"alt":null,"dist":468.8,"pos":0},{"lat":42.6769616,"lon":0.1465344,"alt":null,"dist":494.1,"pos":0},{"lat":42.6771193,"lon":0.146234,"alt":null,"dist":524.3,"pos":0},{"lat":42.6772061,"lon":0.1460195,"alt":null,"dist":544.3,"pos":0},{"lat":42.6772298,"lon":0.1458585,"alt":null,"dist":557.7,"pos":0},{"lat":42.6773638,"lon":0.1456654,"alt":null,"dist":579.4,"pos":0},{"lat":42.67749,"lon":0.1454616,"alt":null,"dist":601.2,"pos":0},{"lat":42.6776084,"lon":0.1453435,"alt":null,"dist":617.6,"pos":0},{"lat":42.6777267,"lon":0.1452041,"alt":null,"dist":635,"pos":0},{"lat":42.6778371,"lon":0.1450217,"alt":null,"dist":654.3,"pos":0},{"lat":42.6779318,"lon":0.1449251,"alt":null,"dist":667.4,"pos":0},{"lat":42.6780106,"lon":0.1447749,"alt":null,"dist":682.5,"pos":0},{"lat":42.6781368,"lon":0.1446033,"alt":null,"dist":702.4,"pos":0},{"lat":42.6783261,"lon":0.1445067,"alt":null,"dist":724.8,"pos":0},{"lat":42.6784208,"lon":0.144335,"alt":null,"dist":742.4,"pos":0},{"lat":42.678547,"lon":0.1441526,"alt":null,"dist":762.9,"pos":0},{"lat":42.6787126,"lon":0.1440024,"alt":null,"dist":785,"pos":0},{"lat":42.6788388,"lon":0.1437986,"alt":null,"dist":806.8,"pos":0},{"lat":42.678965,"lon":0.1436484,"alt":null,"dist":825.4,"pos":0},{"lat":42.6790912,"lon":0.1434445,"alt":null,"dist":847.2,"pos":0},{"lat":42.6792016,"lon":0.1432943,"alt":null,"dist":864.6,"pos":0},{"lat":42.6793594,"lon":0.1431012,"alt":null,"dist":888.2,"pos":0},{"lat":42.6794383,"lon":0.1428759,"alt":null,"dist":908.6,"pos":0},{"lat":42.6796591,"lon":0.1426828,"alt":null,"dist":937.8,"pos":0},{"lat":42.6797222,"lon":0.1425004,"alt":null,"dist":954.2,"pos":0},{"lat":42.6797932,"lon":0.1422322,"alt":null,"dist":977.5,"pos":0},{"lat":42.6799509,"lon":0.1419532,"alt":null,"dist":1006.3,"pos":0},{"lat":42.6799667,"lon":0.1416636,"alt":null,"dist":1030.1,"pos":0},{"lat":42.6800219,"lon":0.1415026,"alt":null,"dist":1044.6,"pos":0},{"lat":42.6802033,"lon":0.1413631,"alt":null,"dist":1067.7,"pos":0},{"lat":42.6803611,"lon":0.14117,"alt":null,"dist":1091.4,"pos":0},{"lat":42.6805425,"lon":0.1411378,"alt":null,"dist":1111.7,"pos":0},{"lat":42.6807002,"lon":0.1410735,"alt":null,"dist":1130,"pos":0},{"lat":42.680858,"lon":0.1409876,"alt":null,"dist":1148.9,"pos":0},{"lat":42.6810473,"lon":0.1408911,"alt":null,"dist":1171.4,"pos":0},{"lat":42.6811971,"lon":0.140816,"alt":null,"dist":1189.1,"pos":0},{"lat":42.6812997,"lon":0.1406336,"alt":null,"dist":1207.9,"pos":0},{"lat":42.6813549,"lon":0.1405156,"alt":null,"dist":1219.3,"pos":0},{"lat":42.6812681,"lon":0.1402259,"alt":null,"dist":1244.9,"pos":0},{"lat":42.6812208,"lon":0.140065,"alt":null,"dist":1259.1,"pos":0},{"lat":42.6811419,"lon":0.1399255,"alt":null,"dist":1273.5,"pos":0},{"lat":42.6809842,"lon":0.1397753,"alt":null,"dist":1294.9,"pos":0},{"lat":42.6809211,"lon":0.13955,"alt":null,"dist":1314.6,"pos":0},{"lat":42.6808107,"lon":0.1393247,"alt":null,"dist":1336.7,"pos":0},{"lat":42.6808343,"lon":0.1390243,"alt":null,"dist":1361.4,"pos":0},{"lat":42.6808974,"lon":0.1388097,"alt":null,"dist":1380.3,"pos":0},{"lat":42.6809605,"lon":0.1386809,"alt":null,"dist":1393,"pos":0},{"lat":42.6810236,"lon":0.1385576,"alt":null,"dist":1405.2,"pos":0},{"lat":42.6811143,"lon":0.1384234,"alt":null,"dist":1420.1,"pos":0},{"lat":42.681205,"lon":0.138343,"alt":null,"dist":1432.2,"pos":0},{"lat":42.6813509,"lon":0.1382625,"alt":null,"dist":1449.7,"pos":0},{"lat":42.6814692,"lon":0.1381713,"alt":null,"dist":1464.8,"pos":0},{"lat":42.681556,"lon":0.1380748,"alt":null,"dist":1477.3,"pos":0},{"lat":42.6816309,"lon":0.1379621,"alt":null,"dist":1489.7,"pos":0},{"lat":42.6816782,"lon":0.1378548,"alt":null,"dist":1499.9,"pos":0},{"lat":42.6817177,"lon":0.1377475,"alt":null,"dist":1509.7,"pos":0},{"lat":42.6817689,"lon":0.1375973,"alt":null,"dist":1523.3,"pos":0},{"lat":42.6818084,"lon":0.1374847,"alt":null,"dist":1533.5,"pos":0},{"lat":42.681836,"lon":0.1373827,"alt":null,"dist":1542.3,"pos":0},{"lat":42.6818399,"lon":0.1372594,"alt":null,"dist":1552.4,"pos":0},{"lat":42.6818557,"lon":0.137136,"alt":null,"dist":1562.7,"pos":0},{"lat":42.6818794,"lon":0.1369911,"alt":null,"dist":1574.8,"pos":0},{"lat":42.6819661,"lon":0.1368517,"alt":null,"dist":1589.7,"pos":0},{"lat":42.6820332,"lon":0.1367497,"alt":null,"dist":1600.9,"pos":0},{"lat":42.6821081,"lon":0.1366854,"alt":null,"dist":1610.8,"pos":0},{"lat":42.6821436,"lon":0.1365405,"alt":null,"dist":1623.2,"pos":0},{"lat":42.6822382,"lon":0.136385,"alt":null,"dist":1639.7,"pos":0},{"lat":42.6822934,"lon":0.1362669,"alt":null,"dist":1651.2,"pos":0},{"lat":42.6823447,"lon":0.1361328,"alt":null,"dist":1663.5,"pos":0},{"lat":42.6823447,"lon":0.1359451,"alt":null,"dist":1678.9,"pos":0},{"lat":42.682321,"lon":0.1357949,"alt":null,"dist":1691.4,"pos":0},{"lat":42.6823368,"lon":0.1356554,"alt":null,"dist":1703,"pos":0},{"lat":42.6823486,"lon":0.1355052,"alt":null,"dist":1715.3,"pos":0},{"lat":42.6823565,"lon":0.1353174,"alt":null,"dist":1730.7,"pos":0},{"lat":42.6824196,"lon":0.135076,"alt":null,"dist":1751.6,"pos":0},{"lat":42.6824512,"lon":0.1348186,"alt":null,"dist":1773,"pos":0},{"lat":42.6824788,"lon":0.1345289,"alt":null,"dist":1796.9,"pos":0},{"lat":42.6824867,"lon":0.134325,"alt":null,"dist":1813.5,"pos":0},{"lat":42.6824591,"lon":0.1341426,"alt":null,"dist":1828.8,"pos":0},{"lat":42.6824078,"lon":0.1339817,"alt":null,"dist":1843.1,"pos":0},{"lat":42.6823684,"lon":0.1338422,"alt":null,"dist":1855.3,"pos":0},{"lat":42.682392,"lon":0.133751,"alt":null,"dist":1863.2,"pos":0},{"lat":42.682396,"lon":0.1336491,"alt":null,"dist":1871.6,"pos":0},{"lat":42.6823881,"lon":0.1334077,"alt":null,"dist":1891.3,"pos":0},{"lat":42.6823486,"lon":0.1332414,"alt":null,"dist":1905.6,"pos":0},{"lat":42.6822895,"lon":0.1330858,"alt":null,"dist":1919.9,"pos":0},{"lat":42.6823053,"lon":0.1328766,"alt":null,"dist":1937.1,"pos":0},{"lat":42.6823131,"lon":0.1326889,"alt":null,"dist":1952.5,"pos":0},{"lat":42.6823605,"lon":0.1325655,"alt":null,"dist":1963.9,"pos":0},{"lat":42.6823762,"lon":0.1324314,"alt":null,"dist":1975,"pos":0},{"lat":42.6824315,"lon":0.1323026,"alt":null,"dist":1987.2,"pos":0},{"lat":42.6825064,"lon":0.1321793,"alt":null,"dist":2000.2,"pos":0},{"lat":42.6825734,"lon":0.1320344,"alt":null,"dist":2014.2,"pos":0},{"lat":42.6826129,"lon":0.1319218,"alt":null,"dist":2024.4,"pos":0},{"lat":42.6826286,"lon":0.1317984,"alt":null,"dist":2034.7,"pos":0},{"lat":42.6826681,"lon":0.1317072,"alt":null,"dist":2043.3,"pos":0},{"lat":42.6827036,"lon":0.1315624,"alt":null,"dist":2055.8,"pos":0},{"lat":42.6827469,"lon":0.1314658,"alt":null,"dist":2065,"pos":0},{"lat":42.6827864,"lon":0.1313317,"alt":null,"dist":2076.8,"pos":0},{"lat":42.6828652,"lon":0.1311386,"alt":null,"dist":2094.9,"pos":0},{"lat":42.6829165,"lon":0.1309776,"alt":null,"dist":2109.2,"pos":0},{"lat":42.6829362,"lon":0.130747,"alt":null,"dist":2128.2,"pos":0},{"lat":42.6829402,"lon":0.1305646,"alt":null,"dist":2143.1,"pos":0},{"lat":42.6829402,"lon":0.1303875,"alt":null,"dist":2157.6,"pos":0},{"lat":42.6829402,"lon":0.130232,"alt":null,"dist":2170.3,"pos":0},{"lat":42.6829204,"lon":0.130071,"alt":null,"dist":2183.7,"pos":0},{"lat":42.6828928,"lon":0.129894,"alt":null,"dist":2198.5,"pos":0},{"lat":42.6829086,"lon":0.1296365,"alt":null,"dist":2219.6,"pos":0},{"lat":42.6829441,"lon":0.1294971,"alt":null,"dist":2231.6,"pos":0},{"lat":42.6829993,"lon":0.1293308,"alt":null,"dist":2246.5,"pos":0},{"lat":42.6830979,"lon":0.1292932,"alt":null,"dist":2257.9,"pos":0},{"lat":42.6831649,"lon":0.1293039,"alt":null,"dist":2265.4,"pos":0},{"lat":42.6832083,"lon":0.1294219,"alt":null,"dist":2276.2,"pos":0},{"lat":42.6832793,"lon":0.1293093,"alt":null,"dist":2288.3,"pos":0},{"lat":42.6833148,"lon":0.1291591,"alt":null,"dist":2301.2,"pos":0},{"lat":42.6832556,"lon":0.1289445,"alt":null,"dist":2320,"pos":0},{"lat":42.6832399,"lon":0.1287836,"alt":null,"dist":2333.2,"pos":0},{"lat":42.6832556,"lon":0.1286173,"alt":null,"dist":2347,"pos":0},{"lat":42.6833069,"lon":0.1283866,"alt":null,"dist":2366.7,"pos":0},{"lat":42.6833818,"lon":0.1281399,"alt":null,"dist":2388.5,"pos":0},{"lat":42.6835238,"lon":0.1279682,"alt":null,"dist":2409.6,"pos":0},{"lat":42.6835987,"lon":0.1277643,"alt":null,"dist":2428.2,"pos":0},{"lat":42.6836736,"lon":0.1276785,"alt":null,"dist":2439.1,"pos":0},{"lat":42.6837841,"lon":0.1274854,"alt":null,"dist":2459.1,"pos":0},{"lat":42.6838748,"lon":0.127303,"alt":null,"dist":2477.1,"pos":0},{"lat":42.6840049,"lon":0.1271635,"alt":null,"dist":2495.5,"pos":0},{"lat":42.6841547,"lon":0.1270723,"alt":null,"dist":2513.8,"pos":0},{"lat":42.6842533,"lon":0.1269168,"alt":null,"dist":2530.6,"pos":0},{"lat":42.6844071,"lon":0.1268095,"alt":null,"dist":2549.8,"pos":0},{"lat":42.6845254,"lon":0.1267022,"alt":null,"dist":2565.6,"pos":0},{"lat":42.6847305,"lon":0.1266325,"alt":null,"dist":2589.1,"pos":0},{"lat":42.6849474,"lon":0.1266056,"alt":null,"dist":2613.3,"pos":0},{"lat":42.685113,"lon":0.1263803,"alt":null,"dist":2639.4,"pos":0},{"lat":42.685109,"lon":0.1261711,"alt":null,"dist":2656.5,"pos":0},{"lat":42.6851682,"lon":0.1260638,"alt":null,"dist":2667.4,"pos":0},{"lat":42.6852037,"lon":0.1258922,"alt":null,"dist":2682,"pos":0},{"lat":42.6852313,"lon":0.1257581,"alt":null,"dist":2693.4,"pos":0},{"lat":42.6852747,"lon":0.1256454,"alt":null,"dist":2703.8,"pos":0},{"lat":42.6853259,"lon":0.1255274,"alt":null,"dist":2715,"pos":0},{"lat":42.6854245,"lon":0.1253611,"alt":null,"dist":2732.5,"pos":0},{"lat":42.6854994,"lon":0.1252806,"alt":null,"dist":2743.1,"pos":0},{"lat":42.6856769,"lon":0.1252592,"alt":null,"dist":2762.9,"pos":0},{"lat":42.6858346,"lon":0.1253611,"alt":null,"dist":2782.3,"pos":0},{"lat":42.6860278,"lon":0.1253825,"alt":null,"dist":2803.9,"pos":0},{"lat":42.6861422,"lon":0.1254523,"alt":null,"dist":2817.8,"pos":0},{"lat":42.6862132,"lon":0.1253933,"alt":null,"dist":2827,"pos":0},{"lat":42.6862999,"lon":0.1252055,"alt":null,"dist":2845.2,"pos":0},{"lat":42.6863117,"lon":0.1250607,"alt":null,"dist":2857.1,"pos":0},{"lat":42.686292,"lon":0.1248407,"alt":null,"dist":2875.2,"pos":0},{"lat":42.6862881,"lon":0.1246798,"alt":null,"dist":2888.4,"pos":0},{"lat":42.6862723,"lon":0.1244599,"alt":null,"dist":2906.4,"pos":0},{"lat":42.6863078,"lon":0.1242775,"alt":null,"dist":2921.8,"pos":0},{"lat":42.6862763,"lon":0.124079,"alt":null,"dist":2938.4,"pos":0},{"lat":42.6862289,"lon":0.1239127,"alt":null,"dist":2953,"pos":0},{"lat":42.6861816,"lon":0.1238269,"alt":null,"dist":2961.8,"pos":0},{"lat":42.6861382,"lon":0.1237035,"alt":null,"dist":2973,"pos":0},{"lat":42.6860988,"lon":0.1235318,"alt":null,"dist":2987.7,"pos":0},{"lat":42.6860515,"lon":0.1234299,"alt":null,"dist":2997.5,"pos":0},{"lat":42.6859332,"lon":0.1233441,"alt":null,"dist":3012.4,"pos":0},{"lat":42.685874,"lon":0.1232851,"alt":null,"dist":3020.6,"pos":0},{"lat":42.6858228,"lon":0.1232046,"alt":null,"dist":3029.3,"pos":0},{"lat":42.6857439,"lon":0.1230973,"alt":null,"dist":3041.7,"pos":0},{"lat":42.6856335,"lon":0.1228613,"alt":null,"dist":3064.6,"pos":0},{"lat":42.6856335,"lon":0.1226306,"alt":null,"dist":3083.4,"pos":0},{"lat":42.6856611,"lon":0.1224214,"alt":null,"dist":3100.8,"pos":0},{"lat":42.6857005,"lon":0.1222605,"alt":null,"dist":3114.6,"pos":0},{"lat":42.6857833,"lon":0.1221639,"alt":null,"dist":3126.8,"pos":0},{"lat":42.6858977,"lon":0.1221049,"alt":null,"dist":3140.4,"pos":0},{"lat":42.6860712,"lon":0.1219976,"alt":null,"dist":3161.6,"pos":0},{"lat":42.6861934,"lon":0.1219815,"alt":null,"dist":3175.2,"pos":0},{"lat":42.6864064,"lon":0.1220351,"alt":null,"dist":3199.3,"pos":0},{"lat":42.6865089,"lon":0.1221156,"alt":null,"dist":3212.5,"pos":0},{"lat":42.6866824,"lon":0.1222819,"alt":null,"dist":3236.1,"pos":0},{"lat":42.6868559,"lon":0.1223731,"alt":null,"dist":3256.8,"pos":0},{"lat":42.68699,"lon":0.122416,"alt":null,"dist":3272.1,"pos":0},{"lat":42.6870688,"lon":0.1224053,"alt":null,"dist":3280.9,"pos":0},{"lat":42.6872266,"lon":0.1223838,"alt":null,"dist":3298.5,"pos":0},{"lat":42.6873133,"lon":0.1223624,"alt":null,"dist":3308.3,"pos":0},{"lat":42.6873646,"lon":0.122357,"alt":null,"dist":3314,"pos":0},{"lat":42.6874553,"lon":0.1224589,"alt":null,"dist":3327.1,"pos":0},{"lat":42.6875105,"lon":0.1225662,"alt":null,"dist":3337.8,"pos":0},{"lat":42.6875972,"lon":0.1226467,"alt":null,"dist":3349.5,"pos":0},{"lat":42.6876998,"lon":0.1226306,"alt":null,"dist":3361,"pos":0},{"lat":42.687818,"lon":0.1225609,"alt":null,"dist":3375.3,"pos":0},{"lat":42.6879324,"lon":0.1227057,"alt":null,"dist":3392.7,"pos":0},{"lat":42.6879837,"lon":0.1228344,"alt":null,"dist":3404.6,"pos":0},{"lat":42.6880191,"lon":0.1229471,"alt":null,"dist":3414.7,"pos":0},{"lat":42.6880783,"lon":0.1230866,"alt":null,"dist":3427.8,"pos":0},{"lat":42.688169,"lon":0.1231563,"alt":null,"dist":3439.4,"pos":0},{"lat":42.6882479,"lon":0.123226,"alt":null,"dist":3449.9,"pos":0},{"lat":42.688307,"lon":0.1232421,"alt":null,"dist":3456.6,"pos":0},{"lat":42.688378,"lon":0.1232851,"alt":null,"dist":3465.2,"pos":0},{"lat":42.6884687,"lon":0.123328,"alt":null,"dist":3475.9,"pos":0},{"lat":42.6884529,"lon":0.1234406,"alt":null,"dist":3485.3,"pos":0},{"lat":42.6884371,"lon":0.1235747,"alt":null,"dist":3496.4,"pos":0},{"lat":42.6884371,"lon":0.1238322,"alt":null,"dist":3517.4,"pos":0},{"lat":42.6884568,"lon":0.1239932,"alt":null,"dist":3530.7,"pos":0},{"lat":42.6884766,"lon":0.124138,"alt":null,"dist":3542.8,"pos":0},{"lat":42.688512,"lon":0.1242936,"alt":null,"dist":3556.1,"pos":0},{"lat":42.6886224,"lon":0.1243311,"alt":null,"dist":3568.7,"pos":0},{"lat":42.6887762,"lon":0.1243687,"alt":null,"dist":3586.1,"pos":0},{"lat":42.6889064,"lon":0.1243579,"alt":null,"dist":3600.6,"pos":0},{"lat":42.6889813,"lon":0.1243418,"alt":null,"dist":3609.1,"pos":0},{"lat":42.689072,"lon":0.1242828,"alt":null,"dist":3620.2,"pos":0},{"lat":42.689139,"lon":0.1242507,"alt":null,"dist":3628.1,"pos":0},{"lat":42.6891903,"lon":0.1241916,"alt":null,"dist":3635.6,"pos":0},{"lat":42.6892533,"lon":0.124197,"alt":null,"dist":3642.6,"pos":0},{"lat":42.6893204,"lon":0.1242292,"alt":null,"dist":3650.5,"pos":0},{"lat":42.6893716,"lon":0.1243204,"alt":null,"dist":3659.9,"pos":0},{"lat":42.6893992,"lon":0.1244706,"alt":null,"dist":3672.6,"pos":0},{"lat":42.6894308,"lon":0.1245832,"alt":null,"dist":3682.4,"pos":0},{"lat":42.6894584,"lon":0.1247174,"alt":null,"dist":3693.8,"pos":0},{"lat":42.6895333,"lon":0.1247549,"alt":null,"dist":3702.7,"pos":0},{"lat":42.6896161,"lon":0.1247549,"alt":null,"dist":3711.9,"pos":0},{"lat":42.6896753,"lon":0.124712,"alt":null,"dist":3719.4,"pos":0},{"lat":42.689762,"lon":0.1246852,"alt":null,"dist":3729.2,"pos":0},{"lat":42.6898921,"lon":0.1247066,"alt":null,"dist":3743.8,"pos":0},{"lat":42.689967,"lon":0.1248354,"alt":null,"dist":3757.2,"pos":0},{"lat":42.6900459,"lon":0.1249427,"alt":null,"dist":3769.6,"pos":0},{"lat":42.6900774,"lon":0.1250231,"alt":null,"dist":3777.1,"pos":0},{"lat":42.6901248,"lon":0.125066,"alt":null,"dist":3783.4,"pos":0},{"lat":42.69018,"lon":0.1251358,"alt":null,"dist":3791.8,"pos":0},{"lat":42.6902509,"lon":0.125109,"alt":null,"dist":3800,"pos":0},{"lat":42.6903456,"lon":0.1250499,"alt":null,"dist":3811.6,"pos":0},{"lat":42.6904363,"lon":0.1250446,"alt":null,"dist":3821.7,"pos":0},{"lat":42.6905033,"lon":0.1251036,"alt":null,"dist":3830.5,"pos":0},{"lat":42.6905979,"lon":0.1252431,"alt":null,"dist":3846,"pos":0},{"lat":42.6906847,"lon":0.1253664,"alt":null,"dist":3860,"pos":0},{"lat":42.6907951,"lon":0.1255006,"alt":null,"dist":3876.5,"pos":0},{"lat":42.6908936,"lon":0.1256132,"alt":null,"dist":3890.8,"pos":0},{"lat":42.6910395,"lon":0.1257473,"alt":null,"dist":3910.3,"pos":0},{"lat":42.691142,"lon":0.1258868,"alt":null,"dist":3926.5,"pos":0},{"lat":42.6912722,"lon":0.1259726,"alt":null,"dist":3942.6,"pos":0},{"lat":42.6914693,"lon":0.1260799,"alt":null,"dist":3966.2,"pos":0},{"lat":42.6915994,"lon":0.1261926,"alt":null,"dist":3983.3,"pos":0},{"lat":42.6917808,"lon":0.1261979,"alt":null,"dist":4003.5,"pos":0},{"lat":42.6918794,"lon":0.1262087,"alt":null,"dist":4014.5,"pos":0},{"lat":42.6919819,"lon":0.1262355,"alt":null,"dist":4026.1,"pos":0},{"lat":42.6921514,"lon":0.1262891,"alt":null,"dist":4045.4,"pos":0},{"lat":42.6923091,"lon":0.1262891,"alt":null,"dist":4063,"pos":0},{"lat":42.6924866,"lon":0.1263964,"alt":null,"dist":4084.6,"pos":0},{"lat":42.6926325,"lon":0.1264393,"alt":null,"dist":4101.2,"pos":0},{"lat":42.6927902,"lon":0.1263803,"alt":null,"dist":4119.4,"pos":0},{"lat":42.6928887,"lon":0.1263052,"alt":null,"dist":4131.9,"pos":0},{"lat":42.6930228,"lon":0.1262462,"alt":null,"dist":4147.6,"pos":0},{"lat":42.6931253,"lon":0.1262569,"alt":null,"dist":4159,"pos":0},{"lat":42.6932791,"lon":0.1262516,"alt":null,"dist":4176.1,"pos":0},{"lat":42.6934723,"lon":0.1262677,"alt":null,"dist":4197.6,"pos":0},{"lat":42.6936339,"lon":0.126332,"alt":null,"dist":4216.4,"pos":0},{"lat":42.693768,"lon":0.1262569,"alt":null,"dist":4232.5,"pos":0},{"lat":42.6938469,"lon":0.1261389,"alt":null,"dist":4245.5,"pos":0},{"lat":42.6939139,"lon":0.126037,"alt":null,"dist":4256.7,"pos":0},{"lat":42.6940598,"lon":0.1260155,"alt":null,"dist":4273,"pos":0},{"lat":42.6943003,"lon":0.1260209,"alt":null,"dist":4299.8,"pos":0},{"lat":42.6944304,"lon":0.1260531,"alt":null,"dist":4314.5,"pos":0},{"lat":42.6945841,"lon":0.1260316,"alt":null,"dist":4331.7,"pos":0},{"lat":42.6947695,"lon":0.1260477,"alt":null,"dist":4352.3,"pos":0},{"lat":42.6948917,"lon":0.1261014,"alt":null,"dist":4366.6,"pos":0},{"lat":42.6950533,"lon":0.1262248,"alt":null,"dist":4387.2,"pos":0},{"lat":42.695215,"lon":0.1263106,"alt":null,"dist":4406.5,"pos":0},{"lat":42.6954121,"lon":0.1263428,"alt":null,"dist":4428.6,"pos":0},{"lat":42.6957591,"lon":0.1264876,"alt":null,"dist":4468.9,"pos":0},{"lat":42.6960232,"lon":0.1265627,"alt":null,"dist":4498.9,"pos":0},{"lat":42.6961533,"lon":0.1266325,"alt":null,"dist":4514.5,"pos":0},{"lat":42.6962282,"lon":0.1266807,"alt":null,"dist":4523.7,"pos":0},{"lat":42.6963386,"lon":0.1268095,"alt":null,"dist":4539.9,"pos":0},{"lat":42.6964254,"lon":0.1267397,"alt":null,"dist":4551.1,"pos":0},{"lat":42.6965042,"lon":0.1266485,"alt":null,"dist":4562.6,"pos":0},{"lat":42.6966225,"lon":0.1265734,"alt":null,"dist":4577.1,"pos":0},{"lat":42.6966856,"lon":0.1264822,"alt":null,"dist":4587.3,"pos":0},{"lat":42.6967842,"lon":0.1264071,"alt":null,"dist":4599.9,"pos":0},{"lat":42.6968354,"lon":0.1263481,"alt":null,"dist":4607.4,"pos":0},{"lat":42.6969813,"lon":0.126434,"alt":null,"dist":4625,"pos":0},{"lat":42.6971272,"lon":0.1264662,"alt":null,"dist":4641.5,"pos":0},{"lat":42.6972375,"lon":0.1264447,"alt":null,"dist":4653.9,"pos":0},{"lat":42.697411,"lon":0.1264232,"alt":null,"dist":4673.2,"pos":0},{"lat":42.6975056,"lon":0.1264018,"alt":null,"dist":4683.9,"pos":0},{"lat":42.6976003,"lon":0.1263267,"alt":null,"dist":4696.1,"pos":0},{"lat":42.6976909,"lon":0.1262569,"alt":null,"dist":4707.7,"pos":0},{"lat":42.6978013,"lon":0.1261979,"alt":null,"dist":4720.8,"pos":0},{"lat":42.697959,"lon":0.1261389,"alt":null,"dist":4739,"pos":0},{"lat":42.6980497,"lon":0.1261175,"alt":null,"dist":4749.3,"pos":0},{"lat":42.6981404,"lon":0.1260692,"alt":null,"dist":4760.1,"pos":0},{"lat":42.6983139,"lon":0.1259673,"alt":null,"dist":4781.1,"pos":0},{"lat":42.6985346,"lon":0.1259404,"alt":null,"dist":4805.8,"pos":0},{"lat":42.6988343,"lon":0.1259029,"alt":null,"dist":4839.2,"pos":0},{"lat":42.6989959,"lon":0.1258385,"alt":null,"dist":4857.9,"pos":0},{"lat":42.6991221,"lon":0.1258278,"alt":null,"dist":4872,"pos":0},{"lat":42.6992285,"lon":0.1258278,"alt":null,"dist":4883.8,"pos":0},{"lat":42.699335,"lon":0.1257581,"alt":null,"dist":4897,"pos":0},{"lat":42.6994256,"lon":0.1257205,"alt":null,"dist":4907.5,"pos":0},{"lat":42.6995242,"lon":0.125699,"alt":null,"dist":4918.6,"pos":0},{"lat":42.6996504,"lon":0.1255971,"alt":null,"dist":4934.9,"pos":0},{"lat":42.6998002,"lon":0.1255113,"alt":null,"dist":4953,"pos":0},{"lat":42.7000485,"lon":0.1253504,"alt":null,"dist":4983.6,"pos":0},{"lat":42.7002181,"lon":0.1253074,"alt":null,"dist":5002.8,"pos":0},{"lat":42.7004112,"lon":0.1252699,"alt":null,"dist":5024.5,"pos":0},{"lat":42.7004901,"lon":0.1252216,"alt":null,"dist":5034.1,"pos":0},{"lat":42.7006478,"lon":0.1250821,"alt":null,"dist":5055,"pos":0},{"lat":42.7008173,"lon":0.1249641,"alt":null,"dist":5076.2,"pos":0},{"lat":42.700975,"lon":0.1248032,"alt":null,"dist":5098.1,"pos":0},{"lat":42.7011642,"lon":0.1246154,"alt":null,"dist":5124.1,"pos":0},{"lat":42.7013535,"lon":0.1244438,"alt":null,"dist":5149.4,"pos":0},{"lat":42.7015821,"lon":0.1243311,"alt":null,"dist":5176.4,"pos":0},{"lat":42.7017753,"lon":0.1242185,"alt":null,"dist":5199.8,"pos":0},{"lat":42.701862,"lon":0.1241809,"alt":null,"dist":5209.9,"pos":0},{"lat":42.7020631,"lon":0.1241004,"alt":null,"dist":5233.2,"pos":0},{"lat":42.7022208,"lon":0.1239932,"alt":null,"dist":5252.8,"pos":0},{"lat":42.7023469,"lon":0.1239181,"alt":null,"dist":5268.2,"pos":0},{"lat":42.7025322,"lon":0.1238,"alt":null,"dist":5290.9,"pos":0},{"lat":42.7026859,"lon":0.1237464,"alt":null,"dist":5308.5,"pos":0},{"lat":42.7027924,"lon":0.123682,"alt":null,"dist":5321.5,"pos":0},{"lat":42.7029501,"lon":0.123623,"alt":null,"dist":5339.7,"pos":0},{"lat":42.7030526,"lon":0.1235265,"alt":null,"dist":5353.6,"pos":0},{"lat":42.7032024,"lon":0.1234138,"alt":null,"dist":5372.6,"pos":0},{"lat":42.7033364,"lon":0.1234406,"alt":null,"dist":5387.6,"pos":0},{"lat":42.7035256,"lon":0.1233763,"alt":null,"dist":5409.3,"pos":0},{"lat":42.7036557,"lon":0.1232582,"alt":null,"dist":5426.7,"pos":0},{"lat":42.7037661,"lon":0.1231778,"alt":null,"dist":5440.6,"pos":0},{"lat":42.7039001,"lon":0.123167,"alt":null,"dist":5455.6,"pos":0},{"lat":42.7040026,"lon":0.1231188,"alt":null,"dist":5467.6,"pos":0},{"lat":42.7041564,"lon":0.1231027,"alt":null,"dist":5484.8,"pos":0},{"lat":42.7043732,"lon":0.1231402,"alt":null,"dist":5509.1,"pos":0},{"lat":42.7044954,"lon":0.1231402,"alt":null,"dist":5522.7,"pos":0},{"lat":42.7046018,"lon":0.1230973,"alt":null,"dist":5535,"pos":0},{"lat":42.7046097,"lon":0.1230007,"alt":null,"dist":5543,"pos":0},{"lat":42.7045782,"lon":0.1229417,"alt":null,"dist":5548.9,"pos":0},{"lat":42.7045112,"lon":0.1228988,"alt":null,"dist":5557.1,"pos":0},{"lat":42.7045151,"lon":0.1227701,"alt":null,"dist":5567.7,"pos":0},{"lat":42.7045939,"lon":0.1226789,"alt":null,"dist":5579.2,"pos":0},{"lat":42.7046412,"lon":0.1225501,"alt":null,"dist":5590.9,"pos":0},{"lat":42.7047122,"lon":0.1224375,"alt":null,"dist":5603.1,"pos":0},{"lat":42.7047556,"lon":0.1223463,"alt":null,"dist":5611.9,"pos":0},{"lat":42.7047989,"lon":0.1222551,"alt":null,"dist":5620.8,"pos":0},{"lat":42.7048778,"lon":0.1221317,"alt":null,"dist":5634.2,"pos":0},{"lat":42.7049251,"lon":0.1220995,"alt":null,"dist":5640.1,"pos":0},{"lat":42.7049921,"lon":0.1219922,"alt":null,"dist":5651.6,"pos":0},{"lat":42.7050157,"lon":0.1219171,"alt":null,"dist":5658.2,"pos":0},{"lat":42.7049724,"lon":0.1218635,"alt":null,"dist":5664.7,"pos":0},{"lat":42.704933,"lon":0.1218045,"alt":null,"dist":5671.3,"pos":0},{"lat":42.7048975,"lon":0.1217508,"alt":null,"dist":5677.2,"pos":0},{"lat":42.7049014,"lon":0.1216704,"alt":null,"dist":5683.7,"pos":0},{"lat":42.7049606,"lon":0.1216006,"alt":null,"dist":5692.5,"pos":0},{"lat":42.7050079,"lon":0.121488,"alt":null,"dist":5703.1,"pos":0},{"lat":42.7050394,"lon":0.1213968,"alt":null,"dist":5711.3,"pos":0},{"lat":42.7050906,"lon":0.1213163,"alt":null,"dist":5720,"pos":0},{"lat":42.7051498,"lon":0.1212412,"alt":null,"dist":5729,"pos":0},{"lat":42.7052247,"lon":0.1211178,"alt":null,"dist":5742.1,"pos":0},{"lat":42.7053272,"lon":0.1210535,"alt":null,"dist":5754.6,"pos":0},{"lat":42.7054178,"lon":0.1209033,"alt":null,"dist":5770.5,"pos":0},{"lat":42.7054573,"lon":0.1208174,"alt":null,"dist":5778.8,"pos":0},{"lat":42.70554,"lon":0.1207101,"alt":null,"dist":5791.5,"pos":0},{"lat":42.7055755,"lon":0.1206136,"alt":null,"dist":5800.3,"pos":0},{"lat":42.7055913,"lon":0.1204687,"alt":null,"dist":5812.3,"pos":0},{"lat":42.7056662,"lon":0.1204956,"alt":null,"dist":5820.9,"pos":0},{"lat":42.7057411,"lon":0.1205224,"alt":null,"dist":5829.5,"pos":0},{"lat":42.705816,"lon":0.1204419,"alt":null,"dist":5840.1,"pos":0},{"lat":42.7058672,"lon":0.1203293,"alt":null,"dist":5850.9,"pos":0},{"lat":42.7058751,"lon":0.1201898,"alt":null,"dist":5862.4,"pos":0},{"lat":42.7058554,"lon":0.1200986,"alt":null,"dist":5870.1,"pos":0},{"lat":42.705883,"lon":0.1200289,"alt":null,"dist":5876.6,"pos":0},{"lat":42.7060249,"lon":0.1199055,"alt":null,"dist":5895.3,"pos":0},{"lat":42.7060959,"lon":0.1198143,"alt":null,"dist":5906.2,"pos":0},{"lat":42.7061984,"lon":0.1197392,"alt":null,"dist":5919.1,"pos":0},{"lat":42.7062654,"lon":0.1195997,"alt":null,"dist":5932.7,"pos":0},{"lat":42.70636,"lon":0.1194763,"alt":null,"dist":5947.3,"pos":0},{"lat":42.7065019,"lon":0.1193637,"alt":null,"dist":5965.6,"pos":0},{"lat":42.7066044,"lon":0.1192617,"alt":null,"dist":5979.7,"pos":0},{"lat":42.7067345,"lon":0.1192027,"alt":null,"dist":5994.9,"pos":0},{"lat":42.7067936,"lon":0.1191598,"alt":null,"dist":6002.4,"pos":0},{"lat":42.7069197,"lon":0.1190364,"alt":null,"dist":6019.7,"pos":0},{"lat":42.7069867,"lon":0.1189077,"alt":null,"dist":6032.6,"pos":0},{"lat":42.7071247,"lon":0.1188165,"alt":null,"dist":6049.6,"pos":0},{"lat":42.7072193,"lon":0.1187092,"alt":null,"dist":6063.3,"pos":0},{"lat":42.7073179,"lon":0.1185536,"alt":null,"dist":6080.1,"pos":0},{"lat":42.7074677,"lon":0.1183873,"alt":null,"dist":6101.6,"pos":0},{"lat":42.7075859,"lon":0.1182693,"alt":null,"dist":6117.9,"pos":0},{"lat":42.7076687,"lon":0.1181406,"alt":null,"dist":6131.9,"pos":0},{"lat":42.7077239,"lon":0.1180172,"alt":null,"dist":6143.7,"pos":0},{"lat":42.7077791,"lon":0.1179153,"alt":null,"dist":6154,"pos":0},{"lat":42.7079801,"lon":0.1177758,"alt":null,"dist":6179.1,"pos":0},{"lat":42.708126,"lon":0.1177329,"alt":null,"dist":6195.7,"pos":0},{"lat":42.7082718,"lon":0.1176202,"alt":null,"dist":6214.3,"pos":0},{"lat":42.708394,"lon":0.1175612,"alt":null,"dist":6228.8,"pos":0},{"lat":42.7085004,"lon":0.1174432,"alt":null,"dist":6244,"pos":0},{"lat":42.7086384,"lon":0.1173413,"alt":null,"dist":6261.5,"pos":0},{"lat":42.7087685,"lon":0.1172447,"alt":null,"dist":6278,"pos":0},{"lat":42.7089459,"lon":0.1171374,"alt":null,"dist":6299.6,"pos":0},{"lat":42.7091035,"lon":0.1170409,"alt":null,"dist":6318.8,"pos":0},{"lat":42.7092297,"lon":0.1169282,"alt":null,"dist":6335.6,"pos":0},{"lat":42.7093558,"lon":0.1167458,"alt":null,"dist":6356,"pos":0},{"lat":42.7094701,"lon":0.1166385,"alt":null,"dist":6371.5,"pos":0},{"lat":42.7096593,"lon":0.1165259,"alt":null,"dist":6394.4,"pos":0},{"lat":42.7097618,"lon":0.1165259,"alt":null,"dist":6405.8,"pos":0},{"lat":42.709746,"lon":0.1162577,"alt":null,"dist":6427.8,"pos":0},{"lat":42.7097421,"lon":0.1161075,"alt":null,"dist":6440.1,"pos":0},{"lat":42.7097579,"lon":0.1159519,"alt":null,"dist":6452.9,"pos":0},{"lat":42.7099392,"lon":0.1159519,"alt":null,"dist":6473.1,"pos":0},{"lat":42.7100062,"lon":0.1159787,"alt":null,"dist":6480.8,"pos":0},{"lat":42.7100811,"lon":0.115968,"alt":null,"dist":6489.2,"pos":0},{"lat":42.7101639,"lon":0.1159143,"alt":null,"dist":6499.4,"pos":0},{"lat":42.7101718,"lon":0.1158071,"alt":null,"dist":6508.2,"pos":0},{"lat":42.7101875,"lon":0.1156569,"alt":null,"dist":6520.6,"pos":0},{"lat":42.7101993,"lon":0.1155066,"alt":null,"dist":6533,"pos":0},{"lat":42.7101796,"lon":0.1153833,"alt":null,"dist":6543.3,"pos":0},{"lat":42.7102309,"lon":0.1151848,"alt":null,"dist":6560.5,"pos":0},{"lat":42.7102624,"lon":0.1150346,"alt":null,"dist":6573.2,"pos":0},{"lat":42.7102979,"lon":0.1148361,"alt":null,"dist":6589.9,"pos":0},{"lat":42.7103807,"lon":0.1148307,"alt":null,"dist":6599.1,"pos":0},{"lat":42.7104556,"lon":0.11482,"alt":null,"dist":6607.5,"pos":0},{"lat":42.7104989,"lon":0.1148361,"alt":null,"dist":6612.5,"pos":0},{"lat":42.7105935,"lon":0.1148576,"alt":null,"dist":6623.2,"pos":0},{"lat":42.7106763,"lon":0.1148415,"alt":null,"dist":6632.5,"pos":0},{"lat":42.710767,"lon":0.1148361,"alt":null,"dist":6642.6,"pos":0},{"lat":42.7108064,"lon":0.1147664,"alt":null,"dist":6649.7,"pos":0},{"lat":42.7108418,"lon":0.1146859,"alt":null,"dist":6657.4,"pos":0},{"lat":42.7108734,"lon":0.1145625,"alt":null,"dist":6668.1,"pos":0},{"lat":42.710897,"lon":0.1143855,"alt":null,"dist":6682.8,"pos":0},{"lat":42.7108891,"lon":0.1142514,"alt":null,"dist":6693.8,"pos":0},{"lat":42.7108694,"lon":0.1141119,"alt":null,"dist":6705.4,"pos":0},{"lat":42.7108024,"lon":0.1141012,"alt":null,"dist":6712.9,"pos":0},{"lat":42.7108261,"lon":0.1142085,"alt":null,"dist":6722,"pos":0},{"lat":42.71083,"lon":0.1143372,"alt":null,"dist":6732.6,"pos":0},{"lat":42.7107867,"lon":0.1144016,"alt":null,"dist":6739.7,"pos":0},{"lat":42.7107275,"lon":0.114466,"alt":null,"dist":6748.1,"pos":0},{"lat":42.7106526,"lon":0.114525,"alt":null,"dist":6757.7,"pos":0},{"lat":42.7106014,"lon":0.1146162,"alt":null,"dist":6767.1,"pos":0},{"lat":42.7105738,"lon":0.1147449,"alt":null,"dist":6778.1,"pos":0},{"lat":42.7104674,"lon":0.1149809,"alt":null,"dist":6800.7,"pos":0},{"lat":42.7104122,"lon":0.1150507,"alt":null,"dist":6809.1,"pos":0},{"lat":42.7103018,"lon":0.1152062,"alt":null,"dist":6826.7,"pos":0},{"lat":42.710156,"lon":0.1153404,"alt":null,"dist":6846.3,"pos":0},{"lat":42.7101126,"lon":0.115512,"alt":null,"dist":6861.1,"pos":0},{"lat":42.7100299,"lon":0.1157427,"alt":null,"dist":6882.1,"pos":0},{"lat":42.7099274,"lon":0.1160002,"alt":null,"dist":6906,"pos":0},{"lat":42.7098249,"lon":0.1161504,"alt":null,"dist":6922.8,"pos":0},{"lat":42.7096633,"lon":0.1163596,"alt":null,"dist":6947.6,"pos":0},{"lat":42.7095568,"lon":0.1165098,"alt":null,"dist":6964.6,"pos":0},{"lat":42.709478,"lon":0.1165795,"alt":null,"dist":6975.1,"pos":0},{"lat":42.7093203,"lon":0.1167512,"alt":null,"dist":6997.6,"pos":0},{"lat":42.7092336,"lon":0.1168424,"alt":null,"dist":7009.7,"pos":0},{"lat":42.709139,"lon":0.1169765,"alt":null,"dist":7024.9,"pos":0},{"lat":42.7089104,"lon":0.1171267,"alt":null,"dist":7053.2,"pos":0},{"lat":42.7087409,"lon":0.1173091,"alt":null,"dist":7077.2,"pos":0},{"lat":42.7085438,"lon":0.1175129,"alt":null,"dist":7104.7,"pos":0},{"lat":42.7082994,"lon":0.1176524,"alt":null,"dist":7134.2,"pos":0},{"lat":42.7080984,"lon":0.1177973,"alt":null,"dist":7159.5,"pos":0},{"lat":42.707917,"lon":0.1179367,"alt":null,"dist":7182.6,"pos":0},{"lat":42.7076569,"lon":0.1182586,"alt":null,"dist":7221.7,"pos":0},{"lat":42.7074204,"lon":0.1185375,"alt":null,"dist":7256.5,"pos":0},{"lat":42.7072509,"lon":0.1186931,"alt":null,"dist":7279.3,"pos":0},{"lat":42.7070419,"lon":0.1189345,"alt":null,"dist":7309.7,"pos":0},{"lat":42.7068921,"lon":0.1191384,"alt":null,"dist":7333.3,"pos":0},{"lat":42.7066753,"lon":0.11931,"alt":null,"dist":7361.2,"pos":0},{"lat":42.7064033,"lon":0.119471,"alt":null,"dist":7394.2,"pos":0},{"lat":42.706289,"lon":0.119648,"alt":null,"dist":7413.4,"pos":0},{"lat":42.7061589,"lon":0.1198357,"alt":null,"dist":7434.5,"pos":0},{"lat":42.7059776,"lon":0.1200664,"alt":null,"dist":7462.1,"pos":0},{"lat":42.7059106,"lon":0.1204741,"alt":null,"dist":7496.2,"pos":0},{"lat":42.7057766,"lon":0.1206458,"alt":null,"dist":7516.7,"pos":0},{"lat":42.7055716,"lon":0.1208818,"alt":null,"dist":7546.6,"pos":0},{"lat":42.7052799,"lon":0.1212734,"alt":null,"dist":7592.1,"pos":0},{"lat":42.7051537,"lon":0.121606,"alt":null,"dist":7622.7,"pos":0},{"lat":42.7051025,"lon":0.1220244,"alt":null,"dist":7657.4,"pos":0},{"lat":42.7048226,"lon":0.1225662,"alt":null,"dist":7711.5,"pos":0},{"lat":42.704724,"lon":0.1230973,"alt":null,"dist":7756.3,"pos":0},{"lat":42.7045782,"lon":0.1232368,"alt":null,"dist":7776.1,"pos":0},{"lat":42.7041918,"lon":0.1235908,"alt":null,"dist":7827.9,"pos":0},{"lat":42.7039987,"lon":0.1238805,"alt":null,"dist":7859.8,"pos":0},{"lat":42.7035572,"lon":0.1238054,"alt":null,"dist":7909.3,"pos":0},{"lat":42.7033088,"lon":0.1237249,"alt":null,"dist":7937.7,"pos":0},{"lat":42.7028121,"lon":0.1237518,"alt":null,"dist":7993,"pos":0},{"lat":42.7025204,"lon":0.1239556,"alt":null,"dist":8029.4,"pos":0},{"lat":42.7020079,"lon":0.1241809,"alt":null,"dist":8089.3,"pos":0},{"lat":42.7016767,"lon":0.1243311,"alt":null,"dist":8128.1,"pos":0},{"lat":42.7012628,"lon":0.1245296,"alt":null,"dist":8176.9,"pos":0},{"lat":42.7009671,"lon":0.1247978,"alt":null,"dist":8216.5,"pos":0},{"lat":42.7005847,"lon":0.1251894,"alt":null,"dist":8269.7,"pos":0},{"lat":42.7002851,"lon":0.1253074,"alt":null,"dist":8304.4,"pos":0},{"lat":42.6998159,"lon":0.1255596,"alt":null,"dist":8360.4,"pos":0},{"lat":42.6996228,"lon":0.1256508,"alt":null,"dist":8383.2,"pos":0},{"lat":42.6993271,"lon":0.1258171,"alt":null,"dist":8418.8,"pos":0},{"lat":42.6991102,"lon":0.1258761,"alt":null,"dist":8443.3,"pos":0},{"lat":42.6988934,"lon":0.1258922,"alt":null,"dist":8467.5,"pos":0},{"lat":42.6986569,"lon":0.1258922,"alt":null,"dist":8493.8,"pos":0},{"lat":42.6983493,"lon":0.1259834,"alt":null,"dist":8528.8,"pos":0},{"lat":42.6980694,"lon":0.1260638,"alt":null,"dist":8560.6,"pos":0},{"lat":42.6979157,"lon":0.1261336,"alt":null,"dist":8578.6,"pos":0},{"lat":42.6976988,"lon":0.1262999,"alt":null,"dist":8606.3,"pos":0},{"lat":42.6974899,"lon":0.126375,"alt":null,"dist":8630.3,"pos":0},{"lat":42.697139,"lon":0.1264232,"alt":null,"dist":8669.5,"pos":0},{"lat":42.6968985,"lon":0.1264286,"alt":null,"dist":8696.3,"pos":0},{"lat":42.6967053,"lon":0.1264286,"alt":null,"dist":8717.8,"pos":0},{"lat":42.6965476,"lon":0.1265359,"alt":null,"dist":8737.4,"pos":0},{"lat":42.6963978,"lon":0.1266325,"alt":null,"dist":8755.8,"pos":0},{"lat":42.6962834,"lon":0.1266325,"alt":null,"dist":8768.5,"pos":0},{"lat":42.6961415,"lon":0.1267022,"alt":null,"dist":8785.3,"pos":0},{"lat":42.6960114,"lon":0.1267558,"alt":null,"dist":8800.4,"pos":0},{"lat":42.6958537,"lon":0.1268363,"alt":null,"dist":8819.2,"pos":0},{"lat":42.6955422,"lon":0.1267236,"alt":null,"dist":8855,"pos":0},{"lat":42.6952741,"lon":0.1266807,"alt":null,"dist":8885,"pos":0},{"lat":42.6949942,"lon":0.12667,"alt":null,"dist":8916.1,"pos":0},{"lat":42.6947064,"lon":0.1264447,"alt":null,"dist":8953.1,"pos":0},{"lat":42.6944659,"lon":0.1262516,"alt":null,"dist":8984.1,"pos":0},{"lat":42.694253,"lon":0.1262248,"alt":null,"dist":9007.9,"pos":0},{"lat":42.6940085,"lon":0.1261067,"alt":null,"dist":9036.7,"pos":0},{"lat":42.6936944,"lon":0.1261979,"alt":null,"dist":9072.5,"pos":0},{"lat":42.6931726,"lon":0.1261818,"alt":null,"dist":9130.5,"pos":0},{"lat":42.692526,"lon":0.1263213,"alt":null,"dist":9203.3,"pos":0},{"lat":42.6920074,"lon":0.1262087,"alt":null,"dist":9261.7,"pos":0},{"lat":42.6916467,"lon":0.1261336,"alt":null,"dist":9302.3,"pos":0},{"lat":42.6912209,"lon":0.1258922,"alt":null,"dist":9353.6,"pos":0},{"lat":42.690866,"lon":0.125683,"alt":null,"dist":9396.6,"pos":0},{"lat":42.6903897,"lon":0.1252216,"alt":null,"dist":9461.6,"pos":0},{"lat":42.6903061,"lon":0.1249105,"alt":null,"dist":9488.7,"pos":0},{"lat":42.6901681,"lon":0.1249051,"alt":null,"dist":9504,"pos":0},{"lat":42.6899355,"lon":0.1248193,"alt":null,"dist":9530.8,"pos":0},{"lat":42.6896871,"lon":0.1248568,"alt":null,"dist":9558.6,"pos":0},{"lat":42.6894663,"lon":0.1246905,"alt":null,"dist":9586.7,"pos":0},{"lat":42.6893598,"lon":0.124433,"alt":null,"dist":9610.8,"pos":0},{"lat":42.6892139,"lon":0.1242667,"alt":null,"dist":9632,"pos":0},{"lat":42.6890877,"lon":0.1241648,"alt":null,"dist":9648.3,"pos":0},{"lat":42.6890207,"lon":0.1237786,"alt":null,"dist":9680.7,"pos":0},{"lat":42.6889694,"lon":0.1234943,"alt":null,"dist":9704.6,"pos":0},{"lat":42.6888393,"lon":0.1233226,"alt":null,"dist":9724.8,"pos":0},{"lat":42.6886422,"lon":0.1231134,"alt":null,"dist":9752.6,"pos":0},{"lat":42.688512,"lon":0.1227647,"alt":null,"dist":9784.6,"pos":0},{"lat":42.6882981,"lon":0.122475,"alt":null,"dist":9818.1,"pos":0},{"lat":42.6880665,"lon":0.1220995,"alt":null,"dist":9858.2,"pos":0},{"lat":42.6878417,"lon":0.1217294,"alt":null,"dist":9897.4,"pos":0},{"lat":42.6876745,"lon":0.1213592,"alt":null,"dist":9932.9,"pos":0},{"lat":42.6872984,"lon":0.1208121,"alt":null,"dist":9994.2,"pos":0},{"lat":42.6870964,"lon":0.1206082,"alt":null,"dist":10022.1,"pos":0},{"lat":42.6869187,"lon":0.1205224,"alt":null,"dist":10043.1,"pos":0},{"lat":42.686612,"lon":0.1206458,"alt":null,"dist":10078.7,"pos":0},{"lat":42.6862065,"lon":0.1209247,"alt":null,"dist":10129.2,"pos":0},{"lat":42.6859253,"lon":0.121091,"alt":null,"dist":10163.3,"pos":0},{"lat":42.6855665,"lon":0.1213592,"alt":null,"dist":10208.8,"pos":0},{"lat":42.6853535,"lon":0.1215631,"alt":null,"dist":10237.8,"pos":0},{"lat":42.6848961,"lon":0.1214236,"alt":null,"dist":10289.9,"pos":0},{"lat":42.6846358,"lon":0.1214772,"alt":null,"dist":10319.2,"pos":0},{"lat":42.6843577,"lon":0.1214451,"alt":null,"dist":10350.2,"pos":0},{"lat":42.6841429,"lon":0.1217669,"alt":null,"dist":10385.7,"pos":0},{"lat":42.6840483,"lon":0.1223624,"alt":null,"dist":10435.5,"pos":0},{"lat":42.6841823,"lon":0.1229042,"alt":null,"dist":10482.3,"pos":0},{"lat":42.684331,"lon":0.1233333,"alt":null,"dist":10521,"pos":0},{"lat":42.6843992,"lon":0.1239341,"alt":null,"dist":10570.7,"pos":0},{"lat":42.6844347,"lon":0.124476,"alt":null,"dist":10615.2,"pos":0},{"lat":42.6843125,"lon":0.1248246,"alt":null,"dist":10646.8,"pos":0},{"lat":42.6840404,"lon":0.1252431,"alt":null,"dist":10692.4,"pos":0},{"lat":42.6838038,"lon":0.1256561,"alt":null,"dist":10735.2,"pos":0},{"lat":42.6836776,"lon":0.1260692,"alt":null,"dist":10771.8,"pos":0},{"lat":42.6834725,"lon":0.1265895,"alt":null,"dist":10820.1,"pos":0},{"lat":42.6832507,"lon":0.1269704,"alt":null,"dist":10859.8,"pos":0},{"lat":42.6830782,"lon":0.1274049,"alt":null,"dist":10900.1,"pos":0},{"lat":42.6828968,"lon":0.1278716,"alt":null,"dist":10943.3,"pos":0},{"lat":42.6826286,"lon":0.1283276,"alt":null,"dist":10991,"pos":0},{"lat":42.6824512,"lon":0.1286495,"alt":null,"dist":11023.9,"pos":0},{"lat":42.6824393,"lon":0.1290357,"alt":null,"dist":11055.5,"pos":0},{"lat":42.6824827,"lon":0.1295078,"alt":null,"dist":11094.4,"pos":0},{"lat":42.6826405,"lon":0.1298618,"alt":null,"dist":11128.3,"pos":0},{"lat":42.68281,"lon":0.1301354,"alt":null,"dist":11157.5,"pos":0},{"lat":42.6828771,"lon":0.1305217,"alt":null,"dist":11189.9,"pos":0},{"lat":42.6827982,"lon":0.1309294,"alt":null,"dist":11224.4,"pos":0},{"lat":42.682676,"lon":0.1313424,"alt":null,"dist":11260.8,"pos":0},{"lat":42.6825892,"lon":0.1317608,"alt":null,"dist":11296.3,"pos":0},{"lat":42.682396,"lon":0.1322007,"alt":null,"dist":11338.2,"pos":0},{"lat":42.6823723,"lon":0.1324689,"alt":null,"dist":11360.3,"pos":0},{"lat":42.6823131,"lon":0.1329088,"alt":null,"dist":11396.9,"pos":0},{"lat":42.6823802,"lon":0.1333112,"alt":null,"dist":11430.6,"pos":0},{"lat":42.6824157,"lon":0.1337028,"alt":null,"dist":11462.8,"pos":0},{"lat":42.6824315,"lon":0.1339656,"alt":null,"dist":11484.4,"pos":0},{"lat":42.6825182,"lon":0.1342767,"alt":null,"dist":11511.6,"pos":0},{"lat":42.6824157,"lon":0.1346362,"alt":null,"dist":11543.1,"pos":0},{"lat":42.6824354,"lon":0.1349688,"alt":null,"dist":11570.4,"pos":0},{"lat":42.6823802,"lon":0.1354247,"alt":null,"dist":11608.2,"pos":0},{"lat":42.682321,"lon":0.1358539,"alt":null,"dist":11643.8,"pos":0},{"lat":42.6822974,"lon":0.1362509,"alt":null,"dist":11676.4,"pos":0},{"lat":42.6820489,"lon":0.1366854,"alt":null,"dist":11721.4,"pos":0},{"lat":42.681903,"lon":0.1370877,"alt":null,"dist":11758.1,"pos":0},{"lat":42.6817894,"lon":0.1375115,"alt":null,"dist":11794.9,"pos":0},{"lat":42.6816282,"lon":0.1379138,"alt":null,"dist":11832.4,"pos":0},{"lat":42.6814626,"lon":0.138182,"alt":null,"dist":11861,"pos":0},{"lat":42.6811222,"lon":0.1384449,"alt":null,"dist":11904.6,"pos":0},{"lat":42.6809211,"lon":0.1387668,"alt":null,"dist":11939.1,"pos":0},{"lat":42.6808738,"lon":0.1390511,"alt":null,"dist":11962.9,"pos":0},{"lat":42.6808974,"lon":0.1393461,"alt":null,"dist":11987.2,"pos":0},{"lat":42.6809921,"lon":0.1397485,"alt":null,"dist":12021.7,"pos":0},{"lat":42.6811814,"lon":0.140081,"alt":null,"dist":12056.1,"pos":0},{"lat":42.6813273,"lon":0.1404297,"alt":null,"dist":12088.9,"pos":0},{"lat":42.6813115,"lon":0.1407355,"alt":null,"dist":12113.9,"pos":0},{"lat":42.6810749,"lon":0.1409179,"alt":null,"dist":12144.2,"pos":0},{"lat":42.6808067,"lon":0.1409984,"alt":null,"dist":12174.7,"pos":0},{"lat":42.6805109,"lon":0.1411378,"alt":null,"dist":12209.5,"pos":0},{"lat":42.6801915,"lon":0.1413095,"alt":null,"dist":12247.7,"pos":0},{"lat":42.680018,"lon":0.1415938,"alt":null,"dist":12277.9,"pos":0},{"lat":42.6799628,"lon":0.141905,"alt":null,"dist":12304.1,"pos":0},{"lat":42.6798011,"lon":0.1423717,"alt":null,"dist":12346.3,"pos":0},{"lat":42.6794856,"lon":0.1427847,"alt":null,"dist":12395,"pos":0},{"lat":42.6792191,"lon":0.1432192,"alt":null,"dist":12441.2,"pos":0},{"lat":42.6789673,"lon":0.1435304,"alt":null,"dist":12479,"pos":0},{"lat":42.6786377,"lon":0.143981,"alt":null,"dist":12531,"pos":0},{"lat":42.6783104,"lon":0.144437,"alt":null,"dist":12583.1,"pos":0},{"lat":42.6780067,"lon":0.1448876,"alt":null,"dist":12633.1,"pos":0},{"lat":42.6777543,"lon":0.1452255,"alt":null,"dist":12672.5,"pos":0},{"lat":42.677565,"lon":0.1455259,"alt":null,"dist":12704.8,"pos":0},{"lat":42.6773205,"lon":0.1458371,"alt":null,"dist":12742,"pos":0},{"lat":42.6770789,"lon":0.1461428,"alt":null,"dist":12778.7,"pos":0},{"lat":42.6768271,"lon":0.1466954,"alt":null,"dist":12831.9,"pos":0},{"lat":42.676441,"lon":0.1471299,"alt":null,"dist":12887.6,"pos":0},{"lat":42.6761531,"lon":0.1472962,"alt":null,"dist":12922.4,"pos":0},{"lat":42.6759953,"lon":0.1474625,"alt":null,"dist":12944.6,"pos":0},{"lat":42.6757114,"lon":0.1477039,"alt":null,"dist":12981.8,"pos":0},{"lat":42.6754313,"lon":0.1480204,"alt":null,"dist":13022.3,"pos":0},{"lat":42.6753051,"lon":0.1482028,"alt":null,"dist":13042.8,"pos":0},{"lat":42.6750409,"lon":0.1484227,"alt":null,"dist":13077.2,"pos":0},{"lat":42.674733,"lon":0.1485354,"alt":null,"dist":13112.7,"pos":0},{"lat":42.6744651,"lon":0.1487446,"alt":null,"dist":13147,"pos":0},{"lat":42.6739523,"lon":0.1488787,"alt":null,"dist":13205.1,"pos":0},{"lat":42.673696,"lon":0.1490343,"alt":null,"dist":13236.3,"pos":0},{"lat":42.6731307,"lon":0.1494518,"alt":null,"dist":13307.8,"pos":0}]