[{"lat":42.6656417,"lon":0.1040053,"alt":null,"dist":0,"pos":0},{"lat":42.6656101,"lon":0.1043057,"alt":null,"dist":24.8,"pos":0},{"lat":42.6655312,"lon":0.1045525,"alt":null,"dist":46.8,"pos":0},{"lat":42.6654997,"lon":0.1047564,"alt":null,"dist":63.9,"pos":0},{"lat":42.665547,"lon":0.1049387,"alt":null,"dist":79.7,"pos":0},{"lat":42.665618,"lon":0.1050782,"alt":null,"dist":93.5,"pos":0},{"lat":42.6657679,"lon":0.1051319,"alt":null,"dist":110.8,"pos":0},{"lat":42.6659573,"lon":0.1050997,"alt":null,"dist":132,"pos":0},{"lat":42.6661229,"lon":0.1050246,"alt":null,"dist":151.4,"pos":0},{"lat":42.666257,"lon":0.1052284,"alt":null,"dist":173.8,"pos":0},{"lat":42.6664148,"lon":0.1054323,"alt":null,"dist":198,"pos":0},{"lat":42.6665489,"lon":0.1055932,"alt":null,"dist":217.9,"pos":0},{"lat":42.6666594,"lon":0.1057434,"alt":null,"dist":235.2,"pos":0},{"lat":42.6668014,"lon":0.1058507,"alt":null,"dist":253.3,"pos":0},{"lat":42.6668803,"lon":0.1061511,"alt":null,"dist":279.4,"pos":0},{"lat":42.666967,"lon":0.1065266,"alt":null,"dist":311.5,"pos":0},{"lat":42.6672511,"lon":0.1068807,"alt":null,"dist":354.4,"pos":0},{"lat":42.6674719,"lon":0.106988,"alt":null,"dist":380.5,"pos":0},{"lat":42.6675903,"lon":0.1071596,"alt":null,"dist":399.7,"pos":0},{"lat":42.6677402,"lon":0.1073098,"alt":null,"dist":420.4,"pos":0},{"lat":42.6678585,"lon":0.1075351,"alt":null,"dist":443.1,"pos":0},{"lat":42.6679611,"lon":0.1077282,"alt":null,"dist":462.5,"pos":0},{"lat":42.6681583,"lon":0.1078355,"alt":null,"dist":486.1,"pos":0},{"lat":42.6682687,"lon":0.1079214,"alt":null,"dist":500.3,"pos":0},{"lat":42.668529,"lon":0.1081574,"alt":null,"dist":535.1,"pos":0},{"lat":42.6686553,"lon":0.1084578,"alt":null,"dist":563.4,"pos":0},{"lat":42.6687973,"lon":0.1086509,"alt":null,"dist":585.7,"pos":0},{"lat":42.6690497,"lon":0.1088655,"alt":null,"dist":618.8,"pos":0},{"lat":42.6692706,"lon":0.1090693,"alt":null,"dist":648.5,"pos":0},{"lat":42.6695309,"lon":0.1092625,"alt":null,"dist":681.5,"pos":0},{"lat":42.669736,"lon":0.1094556,"alt":null,"dist":709.2,"pos":0},{"lat":42.6699411,"lon":0.1096809,"alt":null,"dist":738.5,"pos":0},{"lat":42.6701383,"lon":0.109756,"alt":null,"dist":761.3,"pos":0},{"lat":42.6703434,"lon":0.1098418,"alt":null,"dist":785.1,"pos":0},{"lat":42.6705249,"lon":0.1099062,"alt":null,"dist":806,"pos":0},{"lat":42.6707063,"lon":0.1100028,"alt":null,"dist":827.7,"pos":0},{"lat":42.6708641,"lon":0.1101422,"alt":null,"dist":848.6,"pos":0},{"lat":42.6710534,"lon":0.1102388,"alt":null,"dist":871.1,"pos":0},{"lat":42.6711954,"lon":0.1103246,"alt":null,"dist":888.3,"pos":0},{"lat":42.6713374,"lon":0.1106036,"alt":null,"dist":916.1,"pos":0},{"lat":42.6715109,"lon":0.1107216,"alt":null,"dist":937.6,"pos":0},{"lat":42.6716214,"lon":0.1107001,"alt":null,"dist":950.1,"pos":0},{"lat":42.671787,"lon":0.1105392,"alt":null,"dist":972.7,"pos":0},{"lat":42.6719606,"lon":0.1105177,"alt":null,"dist":992.1,"pos":0},{"lat":42.6720473,"lon":0.1107109,"alt":null,"dist":1010.6,"pos":0},{"lat":42.6721893,"lon":0.110904,"alt":null,"dist":1032.9,"pos":0},{"lat":42.672284,"lon":0.1110327,"alt":null,"dist":1047.8,"pos":0},{"lat":42.6724181,"lon":0.1112258,"alt":null,"dist":1069.5,"pos":0},{"lat":42.6725206,"lon":0.1113868,"alt":null,"dist":1086.9,"pos":0},{"lat":42.672568,"lon":0.1115906,"alt":null,"dist":1104.4,"pos":0},{"lat":42.6725601,"lon":0.1118696,"alt":null,"dist":1127.2,"pos":0},{"lat":42.6726626,"lon":0.1120305,"alt":null,"dist":1144.6,"pos":0},{"lat":42.6727967,"lon":0.1123416,"alt":null,"dist":1174.1,"pos":0},{"lat":42.6728204,"lon":0.1125669,"alt":null,"dist":1192.7,"pos":0},{"lat":42.6729308,"lon":0.1127386,"alt":null,"dist":1211.4,"pos":0},{"lat":42.6730413,"lon":0.1128995,"alt":null,"dist":1229.4,"pos":0},{"lat":42.6730886,"lon":0.1130497,"alt":null,"dist":1242.7,"pos":0},{"lat":42.6731044,"lon":0.1132643,"alt":null,"dist":1260.4,"pos":0},{"lat":42.6731832,"lon":0.1133287,"alt":null,"dist":1270.6,"pos":0},{"lat":42.6733095,"lon":0.1134145,"alt":null,"dist":1286.3,"pos":0},{"lat":42.6733726,"lon":0.1135218,"alt":null,"dist":1297.5,"pos":0},{"lat":42.6734672,"lon":0.1136506,"alt":null,"dist":1312.4,"pos":0},{"lat":42.6735461,"lon":0.1137793,"alt":null,"dist":1326.1,"pos":0},{"lat":42.6736644,"lon":0.1139617,"alt":null,"dist":1346,"pos":0},{"lat":42.6738143,"lon":0.114305,"alt":null,"dist":1378.6,"pos":0},{"lat":42.6738932,"lon":0.1145947,"alt":null,"dist":1403.9,"pos":0},{"lat":42.6739721,"lon":0.1147985,"alt":null,"dist":1422.7,"pos":0},{"lat":42.6741062,"lon":0.1150346,"alt":null,"dist":1447.1,"pos":0},{"lat":42.6742008,"lon":0.1152813,"alt":null,"dist":1469.8,"pos":0},{"lat":42.6742876,"lon":0.1155281,"alt":null,"dist":1492.2,"pos":0},{"lat":42.6743665,"lon":0.1157105,"alt":null,"dist":1509.5,"pos":0},{"lat":42.6745006,"lon":0.1159465,"alt":null,"dist":1533.9,"pos":0},{"lat":42.6746662,"lon":0.1162684,"alt":null,"dist":1566,"pos":0},{"lat":42.674824,"lon":0.1164615,"alt":null,"dist":1589.6,"pos":0},{"lat":42.674895,"lon":0.1166332,"alt":null,"dist":1605.7,"pos":0},{"lat":42.6749738,"lon":0.1167941,"alt":null,"dist":1621.5,"pos":0},{"lat":42.6751198,"lon":0.1169068,"alt":null,"dist":1640.2,"pos":0},{"lat":42.6752105,"lon":0.1171052,"alt":null,"dist":1659.3,"pos":0},{"lat":42.6752933,"lon":0.1173252,"alt":null,"dist":1679.5,"pos":0},{"lat":42.6753525,"lon":0.1174808,"alt":null,"dist":1693.8,"pos":0},{"lat":42.6754787,"lon":0.1176739,"alt":null,"dist":1714.9,"pos":0},{"lat":42.6756167,"lon":0.1178348,"alt":null,"dist":1735.2,"pos":0},{"lat":42.6756995,"lon":0.1179045,"alt":null,"dist":1746,"pos":0}]