{
    "distanceMax": 41,
    "dureeMax": 18,
    "deniveleMax": 3300,
    "nomTypesParcours": [
        "Ida",
        "Ida y Vuelta",
        "Circular"
    ],
    "nomVallees": [
        "Pineta/Refugio",
        "Pineta/Pradera",
        "Salcorz",
        "Barrosa",
        "Trigoniero",
        "Bielsa",
        "Real/Petramula",
        "Pineta/Espierba",
        "Túnel Boca Norte",
        "Pineta/Embalse",
        "Gavarnie/Troumouse",
        "Túnel Boca Sur",
        "Túnel - Barrosa"
    ],
    "difficultePhysiqueMax": 5,
    "difficulteOrientationMax": 4
}